Workbook

Sheet Contributors
A1: Terms describing "roles" or"personas" in FAIR data principle implementation. These are all "stakeholders" in FAIR data principles implementation. The purpose of this document is to collect data that will be sued to update the FAIR maturity matrix framework as well as the FAIR business framework.
B2: Name | C2: Last/Family_Name | D2: Organisation | E2: ORCID | F2: comments | G2: Initials
B3: Ranu | C3: ⁠Sharma | D3: AbbVie | E3: https://orcid.org/0009-0004-6207-0773 | G3: RS
B4: Debashree | C4: Chakrabarti | D4: ABBVIE | E4: {enter your ORCID - takes 2 min to create one} | G4: DC
B5: Kathleen | C5: Rand | D5: AMGEN | E5: {enter your ORCID - takes 2 min to create one} | G5: Amgen
B6: Philippe | C6: Rocca-Serra | D6: Astrazeneca | E6: {enter your ORCID - takes 2 min to create one} | G6: PRS
B7: Baptiste | C7: Tauzin | D7: CSL-Behring | E7: {enter your ORCID - takes 2 min to create one} | G7: BT
B8: Lynch | C8: Nick | D8: Curlew Research | E8: https://orcid.org/0000-0002-8997-5298 | G8: NL
B9: Avinash | C9: Dixit | D9: Datavid | E9: https://orcid.org/0009-0005-8204-6655 | G9: AD
B10: Ted | C10: Slater | D10: EPAM | E10: https://orcid.org/0000-0003-1386-0731 | G10: TS
B11: Buck | C11: Flannigan | D11: Fluree
B12: David | C12: Fernandez Rue | D12: Gruenenthal | E12: https://0009-0007-6684-2605 | G12: DFR
B13: Nalini | C13: Mehta | D13: GSK | E13: https://orcid.org/0000-0002-7553-6569 | G13: NM
B14: Emiliano | C14: Reynares | D14: IQVIA | E14: {enter your ORCID - takes 2 min to create one} | G14: ER
B15: Katharina | C15: Lang | D15: Novo Nordisk | E15: {enter your ORCID - takes 2 min to create one} | G15: KHRL
B16: Karien | C16: Pype | D16: Ontoforce | E16: {enter your ORCID - takes 2 min to create one} | G16: Ontoforce
B17: Chris | C17: Day | D17: Perdl | E17: {enter your ORCID - takes 2 min to create one} | G17: CD
B18: Birgit | C18: Meldal | D18: Pfizer | E18: https://orcid.org/0000-0003-4062-6158 | G18: BM
B19: Giovanni | C19: Nisato | D19: Pistoia Alliance | E19: https://orcid.org/0000-0002-5824-0061 | G19: GN
B20: Tara Kumar | C20: Gajula | D20: Takeda | E20: https://orcid.org/0009-0006-0072-7148 | G20: TKG
B21: John Apathy | C21: Apathy | D21: Xponentl | E21: {enter your ORCID - takes 2 min to create one} | G21: JA

Sheet FAIR_principles_GOFAIR
A1: Source: | B1: https://www.go-fair.org/fair-principles/
A2: Accessed on_YYYY_MM_DD: | B2: 45818
A3: Findable | C3: =A3 -> Findable
A4: The first step in (re)using data is to find them. Metadata and data should be easy to find for both humans and computers. Machine-readable metadata are essential for automatic discovery of datasets and services, so this is an essential component of the FAIRification process.
A5: F1. (Meta)data are assigned a globally unique and persistent identifier | C5: =LEFT(A5,2) -> F1 | D5: =RIGHT(A5,LEN(A5)-4) -> (Meta)data are assigned a globally unique and persistent identifier
A6: F2. Data are described with rich metadata (defined by R1 below) | C6: =LEFT(A6,2) -> F2 | D6: =RIGHT(A6,LEN(A6)-4) -> Data are described with rich metadata (defined by R1 below)
A7: F3. Metadata clearly and explicitly include the identifier of the data they describe | C7: =LEFT(A7,2) -> F3 | D7: =RIGHT(A7,LEN(A7)-4) -> Metadata clearly and explicitly include the identifier of the data they describe
A8: F4. (Meta)data are registered or indexed in a searchable resource | C8: =LEFT(A8,2) -> F4 | D8: =RIGHT(A8,LEN(A8)-4) -> (Meta)data are registered or indexed in a searchable resource
A9: Accessible | C9: =A9 -> Accessible
A10: Once the user finds the required data, she/he/they need to know how they can be accessed, possibly including authentication and authorisation.
A11: A1. (Meta)data are retrievable by their identifier using a standardised communications protocol | C11: =LEFT(A11,2) -> A1 | D11: =RIGHT(A11,LEN(A11)-4) -> (Meta)data are retrievable by their identifier using a standardised communications protocol
A12: A1.1 The protocol is open, free, and universally implementable | C12: =LEFT(A12,4) -> A1.1 | D12: =RIGHT(A12,LEN(A12)-5) -> The protocol is open, free, and universally implementable
A13: A1.2 The protocol allows for an authentication and authorisation procedure, where necessary | C13: =LEFT(A13,4) -> A1.2 | D13: =RIGHT(A13,LEN(A13)-5) -> The protocol allows for an authentication and authorisation procedure, where necessary
A14: A2. Metadata are accessible, even when the data are no longer available | C14: =LEFT(A14,2) -> A2 | D14: =RIGHT(A14,LEN(A14)-4) -> Metadata are accessible, even when the data are no longer available
A15: Interoperable | C15: =A15 -> Interoperable
A16: The data usually need to be integrated with other data. In addition, the data need to interoperate with applications or workflows for analysis, storage, and processing.
A17: I1. (Meta)data use a formal, accessible, shared, and broadly applicable language for knowledge representation. | C17: =LEFT(A17,2) -> I1 | D17: =RIGHT(A17,LEN(A17)-4) -> (Meta)data use a formal, accessible, shared, and broadly applicable language for knowledge representation.
A18: I2. (Meta)data use vocabularies that follow FAIR principles | C18: =LEFT(A18,4) -> I2. | D18: =RIGHT(A18,LEN(A18)-5) -> Meta)data use vocabularies that follow FAIR principles
A19: I3. (Meta)data include qualified references to other (meta)data | C19: =LEFT(A19,4) -> I3. | D19: =RIGHT(A19,LEN(A19)-5) -> Meta)data include qualified references to other (meta)data
A20: Reusable | C20: =A20 -> Reusable
A21: The ultimate goal of FAIR is to optimise the reuse of data. To achieve this, metadata and data should be well-described so that they can be replicated and/or combined in different settings.
A22: R1. (Meta)data are richly described with a plurality of accurate and relevant attributes | C22: =LEFT(A22,2) -> R1 | D22: =RIGHT(A22,LEN(A22)-4) -> (Meta)data are richly described with a plurality of accurate and relevant attributes
A23: R1.1. (Meta)data are released with a clear and accessible data usage license | C23: =LEFT(A23,4) -> R1.1 | D23: =RIGHT(A23,LEN(A23)-5) -> (Meta)data are released with a clear and accessible data usage license
A24: R1.2. (Meta)data are associated with detailed provenance | C24: =LEFT(A24,4) -> R1.2 | D24: =RIGHT(A24,LEN(A24)-5) -> (Meta)data are associated with detailed provenance
A25: R1.3. (Meta)data meet domain-relevant community standards | C25: =LEFT(A25,4) -> R1.3 | D25: =RIGHT(A25,LEN(A25)-5) -> (Meta)data meet domain-relevant community standards
A26: The principles refer to three types of entities: data (or any digital object), metadata (information about that digital object), and infrastructure. For instance, principle F4 defines that both metadata and data are registered or indexed in a searchable resource (the infrastructure component).

Sheet 2025-Personas-FAIR-cleaned
A1: URL/URI of the FAIRpersona | B1: short name of the role [text] | D1: Definition of the role, text. Ideally, this is the same as a known, existing definition we can refer to publicly. | E1: identification of the person that added content in a given line in this document. For internal use, not for ppublic disclosure. | F1: URL/ URI of the text of the definition. (this is a Nice to have for FAIR Maturity Matrix documentation. ) | G1: Known synonyms of this role. Nice to have for FAIR Maturity Matrix documentation. | H1: List of related roles - no hierarchy. Nice to have for FAIR Maturity Matrix documentation and for the FAIR Business Value frame. | I1: Usage in different organisations; non exahustive, just some examples. Nice to have. | J1: Version of the FAIR Maturity Matrix in which this role appears, or recommendation to add to a new version. Based on FAIR expert inputs (organize session for this) | K1: What are the typical tasks, activities or "jobs" of the persona. | L1: Description of the challenges a given persona has with data. | M1: What benefits can FAIR data bring to the persona. | N1: Is the persona necessary in the FAIR MM ? Is it a duplicate? Can it be merged with another persona? | O1: Description of the challenges a given persona has with data. | P1: What benefits can FAIR data bring to the persona. | Q1: document expert group recommendation
A2: FAIRMM-link-MD | B2: Label_persona | C2: Primary data role producer/enabler/consumer | D2: description_of_role | E2: Contributors | F2: Source URL/URI | G2: Synonyms | H2: Related persona | I2: Notes on usage, relation to other roles or personas | J2: FAIRMM-version | K2: Persona_tasks | L2: Issues_latent_gains_draft | M2: Potential_FAIR_benefits_Narrative | N2: Editing comments - Must have/ nice to have / park for the moment | O2: Issues_Latent_gains__Final | P2: Specific-FAIR_benefits_ | Q2: Expert_recommendation_comment | R2: notes | S2: notes2 | T2: notes3
A3: https://github.com/PistoiaAlliance/FAIRMaturityMatrix/blob/FAIR-MM-V1.2/FAIR_personas/Business_analyst.md | B3: Business_Analyst | C3: Data Consumer | D3: The Business Analyst serves as a vital link between business stakeholders and technical teams, ensuring that data, systems, and processes align with organizational goals. They analyze and document business requirements, translate them into data models and workflows, and collaborate across functions to ensure cohesive data design and governance. Skilled in process analysis, requirements engineering, and stakeholder communication, they enable informed decision-making by promoting data quality, consistency, and effective change management. | E3: Avinash Dixit, Debashree Chakrabarti [GN'] | F3: DAMA-DMBOK2: Roles & Responsibilities | G3: Data Modeller; Business System Consultant; Business Relationship Manager; Data Analyst | H3: Advanced_Data_Analysis_and_Insights_Professional,Business_Analyst,Business_Owner,Data_Analyst | I3: Used at : AstraZeneca, Abbvie | J3: { To review with group - V1.2 } | K3: The Business Analyst collaborates across R&D, clinical, regulatory, and IT teams to gather requirements, map workflows, and identify opportunities for process and data improvement. They design compliant data models and specifications, ensure alignment with governance standards, and validate data quality. Additionally, they document processes, support change management, and monitor solution performance to drive continuous improvement in data-driven operations. | L3: Legacy platforms incompatible with new technology. Scientists / users of technology fail to prioritize upkeep. | M3: Business Analyst in a pharmaceutical company, adopting FAIR principles transforms data management into a scalable, proactive discipline. Findable and Accessible data reduce redundancy by eliminating silos and duplication of effort, while Interoperable data—structured through shared ontologies—prevents vendor lock-in and enables seamless integration across diverse platforms and partners. Reusable and well-documented datasets support reproducibility, compliance, and efficient lifecycle management, allowing petabytes of research, clinical, and manufacturing data to be managed and archived systematically through defined policies. With FAIR in place, the Business Analyst can focus on driving business value—optimizing processes, improving data quality, and ensuring that insights are derived from consistent, traceable, and reusable information across the enterprise. | N3: {[GN] should this role be defined more broadly? | O3: Issues: fragmented data silos, poor metadata, inconsistent standards, and limited interoperability—leading to rework, inefficiencies, compliance risks, and slow decision-making. Latent gains: improve data discoverability, consistency, and traceability; reducing redundancy and vendor lock-in; and enabling efficient management of large, diverse datasets through shared ontologies and archiving policies. Increase ability to work proactively, streamline workflows, ensure regulatory readiness, and deliver faster, more reliable insights across the R&D and product lifecycle. | P3: F2 improves discoverability of datasets for analytical use; A1.1 provides standardized metadata protocols for access; R1.2 ensures lawful reuse through explicit licensing clarity
A4: https://github.com/PistoiaAlliance/FAIRMaturityMatrix/blob/FAIR-MM-V1.2/FAIR_personas/Business_Leader.md | B4: Business_Leader | C4: Data Consumer | D4: In an organization, personnel holding roles such as CEO, CFO, CTO, COO, or Functional Line Leaders with executive and strategy level decision- making capacities. | E4: John Apathy, giovanni.nisato / Karien Pype | F4: https://www.wikidata.org/wiki/Q484876 | G4: Chief Executive Officer (CEO); Chief Operating Officer (COO); Chief Financial Officer (CFO); Functional Line Leader; Head of R&D; Head of Manufacturing; Head of CMC; Head of Supply Chain Operations; | H4: Business_Analyst,Business_Leader,Business_Owner,Project_Manager,Technology_Leader | I4: Used at: all companies | J4: { To review with group - V1.2 } | K4: Making data-driven strategic decisions, performance and KPI management, engaging with investors and stakeholders with reliable data, enabling digital and data transformation, managing risk and compliance, supporting M&A, licensing, and due diligence | L4: Data fragmentation, data in silos, poor data re-usability, lack in visibility into data (which data do we have? Can we trust it?), barriers for scaling AI/ML initiatives, compliance and data governance risks | M4: For Business Leaders in a pharmaceutical company, implementing FAIR data principles delivers strategic, operational, and financial advantages: 1- establish a foundation for digital transformation, enabling enterprise-wide data integration across R&D, manufacturing, regulatory, and commercial operations. Executives gain trusted, real-time visibility into the organization’s data assets, accelerating strategic decision-making and reducing dependency on fragmented systems or manual reporting. 2- drive innovation and speed-to-market by making high-quality data readily reusable for AI, machine learning, and predictive modeling—shortening development cycles, improving clinical trial design, and identifying portfolio opportunities faster. 3- reduce operational costs and risks by minimizing data duplication, automating data governance, and enabling scalable management of petabytes of information under consistent standards and archiving policies. 4- enhance regulatory compliance, audit readiness, and partner interoperability, positioning the organization as a trusted, data-driven leader in a rapidly evolving digital health ecosystem. | N4: must have | O4: Issues: Data fragmentation, data in silos, poor data re-usability, lack in visibility into data (which data do we have? Can we trust it?), barriers for scaling AI/ML initiatives, compliance and data governance risks. Latent gains: implementing FAIR principles would reduce these challenges and unlock efficiency, compliance, and reuse. | P4: F1. Enables enterprise-wide data traceability and eliminates duplication, giving executives visibility and accountability for all critical data assets. ; F2. Improves data discoverability and context, accelerating evidence-based decision-making across R&D, clinical, and manufacturing domains.; F3. Strengthens data lineage and provenance, ensuring trustworthy, audit-ready information for regulatory compliance.; F4. Provides centralized visibility of data assets through searchable catalogs and dashboards for strategic oversight and resource planning.; A1. Ensures consistent, standardized access to validated data across systems, reducing manual effort and delays.; A2. Balances open access with secure authorization, protecting intellectual property and patient data while enabling collaboration.; I1. Promotes seamless data exchange across functions, reducing vendor lock-in and integration costs.; I2. Standardizes vocabularies and formats, supporting scalable data governance and automation at petabyte scale.; I3. Connects datasets through qualified references, revealing relationships across the value chain for portfolio and pipeline optimization.;R1. Ensures data are complete, accurate, and meaningful for reuse in analytics, AI, and digital innovation.; R1.1. Clarifies data usage rights, reducing legal uncertainty and enabling confident external collaboration.; R1.2. Provides full provenance for audit trails, reinforcing data integrity and regulatory readiness.; R1.3. Aligns data with community and regulatory standards (e.g., CDISC, IDMP), ensuring compliance and interoperability.;
A5: https://github.com/PistoiaAlliance/FAIRMaturityMatrix/blob/FAIR-MM-V1.2/FAIR_personas/Business_Owner.md | B5: Business_Owner | C5: Data Consumer | D5: The Business Owner is an executive-level business role accountable for the value, performance, and strategic success of a defined business process, product, system, or dataset. As the designated authority within their domain, the Business Owner ensures that data and processes deliver measurable business value, meet defined KPIs, and align with organizational objectives and regulatory requirements. In accordance with DAMA-DMBOK2, the Business Owner is responsible for defining business requirements, approving data standards and policies, and ensuring that data is managed as a strategic enterprise asset. They collaborate with Data Stewards, Architects, and IT teams to translate business needs into data capabilities, oversee the quality and fitness-for-purpose of data, and drive continuous improvement. By championing sound data governance and FAIR-aligned practices, the Business Owner ensures that information assets are consistent, compliant, and reusable—enabling efficient decision-making, regulatory confidence, and sustained business value generation across the organization. | E5: Kathleen Rand , Chris Day / GN re-editing | F5: DAMA-DMBOK2: Appendix A: Roles & Responsibilities Matrix | G5: Business Data Owner; Data Asset Owner; Business Executive & Manager; Executive Sponsor; | H5: FAIR_Data_Architect,Business_Analyst,Data_Analyst,Business_Leader,Data_Owner,Data_Standards_and_Governance_Expert,Subject_Matter_Expert,Project_Manager | I5: Used at : Amgen Used within DAMA DMBoKV2 | J5: { To review with group - V1.2 } | K5: The Business Owner performs a set of core tasks that ensure data, processes, and systems within their domain deliver measurable business value and align with corporate and regulatory expectations. Their tasks include defining business requirements and objectives for data and digital initiatives, ensuring they support strategic priorities. They evaluate and track business value and KPIs, measuring the performance and success of data-driven processes and products. The Business Owner also approves and enforces data policies, standards, and quality rules, guaranteeing that information is accurate, complete, and business-ready. They collaborate with Data Stewards, Data Architects, and IT teams to translate business needs into practical governance and data management solutions. Additionally, they prioritize and sponsor data initiatives, allocate resources, and resolve cross-functional challenges related to data ownership, access, and quality—driving continuous improvement and ensuring that data assets contribute directly to organizational goals. | L5: 1. Unclear Business Ownership of Data Assets FAIR View: Without clear ownership, stewardship for making data Findable, Accessible, Interoperable, and Reusable is often neglected. DAMA View: Data Ownership (within Data Governance) must be clearly defined, yet business owners are often unaware or unclear about their responsibilities. Impact: Data is treated as a by-product, not an asset, hindering strategic data enablement. 2. Lack of Alignment Between Business Goals and Data Strategy FAIR View: FAIRification efforts may be driven by IT or compliance teams, not aligned with value streams or KPIs that matter to business owners. DAMA View: Poor alignment across Data Strategy, Business Process Management, and Data Governance. Impact: Investments in FAIR may appear technical or academic, with unclear ROI for the business owner. 3. Data is Not Trusted or Understood FAIR View: If metadata and provenance are absent or poor, trust is undermined. DAMA View: Data Quality and Metadata Management are foundational, yet often fragmented. Impact: Business owners cannot rely on data for critical decision-making, reducing willingness to sponsor data initiatives. 4. Inconsistent Data Accessibility Across Functions FAIR View: Access policies are inconsistent, siloed, or not machine-actionable. DAMA View: Access & Security Management is often reactive, not driven by business use cases. Impact: Business owners encounter roadblocks or delays when accessing the data they are accountable for, impacting operational agility. 5. Data Silos Obstruct Reuse and Interoperability FAIR View: Poor interoperability blocks data integration and reuse across functions or systems. DAMA View: Reference and Master Data Management is often insufficient, leading to duplication and reconciliation overhead. Impact: Business owners can't extract cross-domain insights or scale analytics and AI initiatives. 6. Lack of Skills and Capacity to Interpret FAIR Metrics FAIR View: Maturity assessments and metrics may seem abstract or disconnected from business outcomes. DAMA View: Literacy gaps in both data management and data value communication. Impact: Business owners struggle to justify ongoing FAIR investment or demonstrate value to executive stakeholders. 7. Regulatory and Compliance Burden without Strategic Leverage FAIR View: Compliance is often a reactive cost centre rather than an opportunity to enhance FAIR maturity. DAMA View: Regulatory alignment is part of Governance and Risk Management but is rarely used as a FAIR catalyst. Impact: FAIR seen as a cost rather than a business enabler, unless reframed. 8. No Clear Business Value Framework for FAIR Data FAIR View: FAIR Maturity Models exist, but are not always coupled to business value frameworks like VMM or ROI calculations. DAMA View: Business Value Realisation is often implicit and not operationalised within Data Governance. Impact: Business owners cannot link FAIR efforts to quantifiable business drivers (e.g. revenue, speed to market, cost reduction). | M5: For a Business Owner, adopting FAIR data principles delivers both strategic and operational value by turning data into a reliable, reusable business asset. Findable and Accessible data accelerate evidence-based decision-making and reduce time spent locating or validating information, improving responsiveness and time-to-market. Enhanced metadata and provenance increase trust, data quality, and regulatory compliance while reducing audit risk and operational errors. Interoperable data promote collaboration and cross-functional reporting, supporting integration during organizational changes or mergers. Through reusability, FAIR minimizes data duplication, lowers operational costs, and improves ROI on data investments. By making data machine-actionable, FAIR enables automation, AI, and innovation, enhancing forecasting, modeling, and digital transformation. Finally, improved traceability and lifecycle stewardship reinforce transparency, governance, and enterprise resilience. Together, these capabilities empower the Business Owner to maximize business value, ensure compliance, and drive sustainable growth. | N5: must have | O5: Issues: Business Owners often face unclear accountability for data assets, leading to neglected stewardship and missed opportunities. Data is frequently treated as a by-product rather than a strategic asset, limiting its contribution to business value. Inconsistent metadata, poor provenance, and fragmented data quality management erode trust and make data unreliable for decision-making. Access policies are uneven and siloed, hindering operational agility, while weak interoperability and duplicate datasets prevent cross-domain insight generation. Additionally, limited literacy in FAIR principles and data governance frameworks leaves Business Owners unable to interpret metrics or demonstrate value. As a result, compliance efforts become reactive cost centers, and FAIR maturity remains disconnected from measurable business outcomes. Paradoxically, even FAIR initiatives aimed to improve the sitation may be driven by IT or compliance functions without alignment to core business goals or KPIs, creating the perception of limited ROI. Latent Gains: Implementing FAIR principles establishes clear business data ownership and embeds stewardship as a core governance function. Data becomes an enterprise asset: traceable, high-quality, and aligned with business objectives. Standardized metadata, access protocols, and interoperable systems ensure consistency, trust, and agility across departments. FAIR maturity strengthens regulatory compliance, turning oversight into strategic advantage through transparent provenance and auditability. Empowered by reliable, well-documented data, Business Owners can link FAIR investments directly to performance indicators such as reduced time-to-insight, faster innovation cycles, and lower operational risk. With improved data literacy and measurable ROI, FAIR transforms data management from a technical exercise into a business enabler, driving sustained efficiency, compliance, and value creation across the organization. | P5: F1 provides persistent identifiers that ensure KPIs and metrics are based on unambiguous, trusted datasets; A1 guarantees reliable access to the data needed for monitoring performance and driving improvements; R1.1 ensures reproducibility of results so business decisions can be defended and audited; R1.2 clarifies licensing and reuse conditions, enabling safe and efficient exploitation of data assets for innovation and partnerships.
A6: https://github.com/PistoiaAlliance/FAIRMaturityMatrix/blob/FAIR-MM-V1.2/FAIR_personas/Citizen_Data_Scientist.md | B6: Citizen_Data_Scientist | C6: Data Producer | D6: Non-expert business user applying self-service analytics tools and dashboards; highly competent but not data-science trained. Individual within an organization who, despite lacking formal training in data science, utilizes data analysis tools and techniques to extract insights from data. These individuals often come from various backgrounds, such as business, marketing, or operations, and possess domain-specific expertise. Citizen Data Scientists leverage self-service analytics platforms, intuitive data visualization tools, and automated machine learning algorithms to explore datasets, generate reports, and uncover patterns or trends relevant to their roles. | E6: giovanni.nisato@pistoiaalliance.org/ Emiliano Reynares / Debashree Chakrabarti | F6: https://pistoiaalliance.github.io/FAIRMaturityMatrix/resources_lexicon | G6: R&D Data Scientist; Applied Data Scientist; ML Scientist | H6: Advanced_Data_Analysis_and_Insights_Professional,Citizen_Data_Scientist,Legal_Data_Expert,Researcher | I6: CDS role will be empowered by GenAI, since natural languages interfaces and automation will lower technical barriers to build models, analyze data, and generate insights. | J6: FAIRMM_V1.1 | K6: Explores and visualize data, combines and clean data in collaboration with data teams, build dashboards, applies automated machine learning, and interpretes results to support business decisions. Performs all of the above using self-service tools without needing to code. | L6: 1. Sources of information lacking complete dataset 2. Context is missed or misinterpreted 3. Often requires additional SME to verify the reports generated, track down original data owners | M6: FAIR principles transforms how data can be accessed, understood, and used. FAIR data ensures that relevant datasets are findable and well-documented, allowing non-technical users to quickly locate trustworthy information without relying on data specialists. With accessible and standardized formats, self-service analytics tools and dashboards can easily connect to validated data sources, reducing the need for manual preparation or IT intervention. Interoperable data, structured through shared vocabularies and ontologies, ensures that metrics and definitions are consistent across business units—making analyses more reliable and comparable. Finally, reusable and well-described data enable repeatable analyses, support automation through AI-assisted tools, and foster confident, compliant decision-making. In short, FAIR empowers Citizen Data Scientists to work independently and efficiently, transforming domain expertise into actionable, data-driven insights without compromising data quality or governance. | O6: Issues: Information sources often lack complete datasets, leading to gaps and inconsistencies. Context is frequently missed or misinterpreted, making analysis and reporting unreliable. Project teams often need to involve additional subject matter experts to verify reports or trace original data owners. Latent gains: Implementing FAIR principles would minimize these challenges by improving data completeness, contextual clarity, and traceability—unlocking greater efficiency, compliance, and data reuse. | P6: F1 ensures that self-service tools pull from datasets with persistent identifiers, avoiding confusion and duplication; F2 provides rich metadata so non-expert users can quickly assess relevance, context, and quality of datasets; A1 guarantees seamless access to trusted data products without technical barriers; I1 enables smooth integration of datasets from different domains into dashboards and tools; R1.1 assures reproducibility of results, giving confidence that insights drawn from self-service analytics are reliable and defensible.
A7: https://github.com/PistoiaAlliance/FAIRMaturityMatrix/blob/FAIR-MM-V1.2/FAIR_personas/Clinical_Data_Manager.md | B7: Clinical_Data_Manager | C7: Data Producer | D7: Ensures accuracy, integrity, and reliability of data collected during clinical trials. They are responsible for designing and maintaining data management plans, overseeing data collection systems, and implementing quality control processes to ensure compliance with regulatory standards and requirements (e.g. from FDA,EMA). They manage the end-to-end data lifecycle in clinical trials. | E7: Ranu Sharma/ Giovanni Nisato ; AD | F7: http://purl.obolibrary.org/obo/NCIT_C142438 AND http://purl.obolibrary.org/obo/NCIT_C51820 | G7: Clinical Data Lead; CDISC Specialist; Clinical Informatics Lead | H7: Business_Owner,Data_manager,Lab_Manager,Project_Manager | I7: Used at AbbVie | J7: { To review with group - V1.2 } | K7: Clinical Data Manager (CDM) plays a central role in ensuring that clinical trial data is complete, accurate, and compliant with global regulatory standards. Their responsibilities include designing and managing case report forms (CRFs), overseeing electronic data capture (EDC) systems, validating incoming data from multiple sites, transforming raw data into standardized submission formats such as CDISC SDTM and ADaM. They coordinate with biostatisticians, clinical operations, medical writers, and regulatory teams to ensure data consistency, timeliness, and readiness for regulatory submissions across complex, multi-country studies. CDMs also monitor data integrity, manage queries and discrepancies, and document all processes to maintain an auditable trail. | L7: face substantial challenges due to the scale and complexity of their trials. Data often comes from heterogeneous sources, including EDCs, laboratory systems, imaging platforms, wearables, and patient-reported outcomes, each using different formats, terminologies, and standards. Reconciling these sources is time-intensive, error-prone, and requires extensive manual mapping. Inconsistent metadata, limited provenance tracking, and siloed data systems make it difficult to ensure data quality, traceability, and reuse across studies. These challenges can lead to delays in submissions, increase operational risk, and limit the ability to leverage historical data for future trials or real-world evidence generation. | M7: By ensuring that data and metadata are findable, accessible, interoperable, and reusable, Clinical_Data_Manager can automate and accelerate data integration and cleaning processes. Standardized vocabularies and ontologies facilitate cross-study comparisons and reduce mapping errors, while rich provenance tracking enhances audit readiness and regulatory confidence. FAIR data also enables better reuse of clinical trial datasets for secondary research, machine learning, and meta-analyses, ultimately supporting faster decision-making, reducing redundancy, and increasing the value derived from every clinical trial. | N7: must have | O7: Issues: face challenges due to the scale and complexity of their trials. Data often comes from heterogeneous sources, including EDCs, laboratory systems, imaging platforms, wearables, and patient-reported outcomes, each using different formats, terminologies, and standards. Reconciling these sources is time-intensive, error-prone, and requires extensive manual mapping. Inconsistent metadata, limited provenance tracking, and siloed data systems make it difficult to ensure data quality, traceability, and reuse across studies. These challenges can lead to delays in submissions, increase operational risk, and limit the ability to leverage historical data for future trials or real-world evidence generation. Latent gains: implementing FAIR principles would reduce these challenges and unlock efficiency, compliance, and reuse. | P7: F1 ensures patient and study data are persistently identified, enabling full traceability across trial phases; F2 provides rich metadata that documents study protocols, variables, and context for regulatory submissions; Findable (F1–F4): Standardized metadata and dataset identifiers make clinical trial data easier to locate across studies, sites, and systems. This ensures that data can be efficiently discovered for ongoing trials, regulatory submissions, or secondary research; A1 guarantees secure but reliable access to trial data for authorized stakeholders, maintaining audit trails and compliance with privacy regulations (GDPR, HIPAA); A2 Metadata remains accessible even if the underlying data is restricted, supporting transparency and planning; I1 supports interoperability between clinical trial management systems, EDC platforms, and regulatory systems ; I3 Adoption of CDISC standards, controlled vocabularies (MedDRA, SNOMED CT), and ontologies. Reduces mapping errors and allows cross-study comparisons and multi-study analyses; R1.1 ensures reproducibility of trial records and analyses, meeting strict compliance requirements; R1.3: Well-documented provenance, data quality metrics, and usage licenses make datasets suitable for regulatory submissions, meta-analyses, and machine learning applications. This increases the long-term value of clinical data and supports reproducibility.
A8: https://github.com/PistoiaAlliance/FAIRMaturityMatrix/blob/FAIR-MM-V1.2/FAIR_personas/Curator.md | B8: Curator | C8: Data Enabler | D8: Organizes, standardises, integrates, and maintains ontologies, vocabularies, datasets and data products to ensure they are FAIR and aligned with governance standards. | E8: Birgit Meldal | F8: Copilot and Birgit: http://purl.obolibrary.org/obo/NCIT_C69141 https://www.wikidata.org/wiki/Q674426 | G8: Data Curator; Biocurator; Knowledge Curator | H8: Data_Standards_and_Governance_Expert,Data_Steward,Knowledge-Enabled_Citizen,Ontologist | I8: Usage in different organisations | J8: { To review with group - V1.2 } | K8: designs and implements curation guidelines; works very closely with stewards and governance personas | L8: data are not aligned or based on domain/global standards. This creates additional work at the very least. | M8: FAIR data principles enhance the efficiency and impact of knowledge management. Rich metadata improves dataset discoverability and context, ensuring curated assets are easily found and understood. Interoperability across knowledge sources enables consistent integration and alignment, while adherence to community standards promotes the reuse and long-term value of curated data assets. | N8: must have | O8: Issues: data are not aligned or based on domain/global standards. This creates additional work at the very least.. Latent gains: implementing FAIR principles would reduce these challenges and unlock efficiency, compliance, and reuse. | P8: F2 enriches metadata to improve dataset discoverability; I1 ensures compatibility across curated knowledge sources; R1.3 promotes reuse of curated assets via community standards
A9: https://github.com/PistoiaAlliance/FAIRMaturityMatrix/blob/FAIR-MM-V1.2/FAIR_personas/Data_Analyst.md#description-of-fair-benefits-fordata_analyst | B9: Data_Analyst | C9: Data Consumer | D9: [RS]: Data Analyst is responsible for designing, developing, and maintaining dashboards and recurring reports that support business needs. Leveraging FAIR data principles, this role collects, cleans, and integrates high-quality data into analytical models and data pipelines. The Data Analyst ensures data is well-documented, traceable, and accessible for a variety of stakeholders, enabling robust analysis and clear, actionable insights for strategic decision-making. Additionally, they collaborate with data engineers and business partners to continuously improve data processes, enhance data usability, and maximize the value of analytics within the organization. | E9: Ranu Sharma, Ted Slater | F9: https://www.wikidata.org/wiki/Q77293133 | G9: Data Scientist; Insights Analyst; Business Intelligence Analyst; Data Analysis and Insights Manager; Senior Data Analyst; Real World Evidence Specialist; Real World Data Analyst; Health Data Manager Real World Data Analyst; Health Data Manager | H9: Advanced_Data_Analysis_and_Insights_Professional,Business_Analyst,Data_Analyst,Data_Integration_Specialist,Data_Owner | I9: Used at AbbVie | J9: { To review with group - V1.2 } | K9: [RS]: Data Analyst sources, prepares, and integrates data from multiple systems into analytical models and pipelines, ensuring data quality and accessibility. They build and maintain dashboards and reports, verify outputs for accuracy, and make insights available to stakeholders. The role also promotes FAIR data principles and collaborates with others to improve data processes and usability. | L9: Unexpected issues in source data; lack of documentation or metadata in source data; problems with workflows, pipelines, or models | M9: Supports FAIR data implementation by ensuring data is consistently documented with comprehensive metadata to enhance findability and reusability. They also facilitate data integration and interoperability by adhering to standardized data formats and collaborating with other teams to optimize data accessibility. {()} {[( F1, A1, I1, R1.1 )]} – F1 provides general benefit for this role; A1 provides general benefit for this role; I1 provides general benefit for this role; R1.1 provides general benefit for this role. | N9: [GN] combine with "Advanced_Data_Analysis_and_Insights_Professiona". | O9: Issues: Unexpected issues in source data; lack of documentation or metadata in source data; problems with workflows, pipelines, or models. Latent gains: implementing FAIR principles would reduce these challenges and unlock efficiency, compliance, and reuse. | P9: F1 ensures that reports are always built on unambiguous datasets with persistent identifiers, avoiding duplication of metrics; F2 provides metadata that makes it easier to understand the business meaning and quality of data, ensuring accurate reporting; A1 guarantees analysts have seamless access to the datasets they need, reducing delays in producing dashboards and KPIs; I1 allows combining data from different domains into integrated views for stakeholders; R1.1 assures that reports are reproducible and can be validated over time, strengthening trust in recurring insights.
A10: https://github.com/PistoiaAlliance/FAIRMaturityMatrix/blob/FAIR-MM-V1.2/FAIR_personas/Data_Owner.md | B10: Data_Owner | C10: Data Enabler | D10: Business-accountable role responsible for the value, quality, and compliance of a dataset} accountable for the data within a specific domain or dataset. This includes the quality, integrity, access control, compliance (to standards and FAIR) and usage policies of the data. [RS]: In the context of FAIR data principles, a Data Owner has both the legal rights and managerial responsibility for a dataset. The Data Owner is responsible for establishing policies on who can access and use the data, ensuring compliance with relevant laws and standards, and managing permissions. They oversee the assignment of metadata, documentation, and maintenance of data quality, while ultimately being accountable for the dataset’s proper stewardship, even if routine management is delegated to others, ensuring the data remains FAIR-compliant at all times. | E10: Kathleen R and, Nalini Mehta, Baptiste Tauzin | F10: https://datamanagement.wiki/role/data_owner https://www.gov.uk/government/publications/essential-shared-data-assets-and-data-ownership-in-government/data-ownership-in-government-html | G10: Business Data Owner; Data Asset Owner; Data Manager | H10: Business_Leader,Business_Owner,Business_Analyst,Data_Steward,Project_Manager | I10: Used at : Amgen, GSK | J10: { To review with group - V1.2 } | K10: [RS] : Oversees organizational data assets, setting and enforcing policies on data access, quality, security, and retention to align with business goals and compliance standards. Defines data governance protocols, approves data classifications, and manages risk by implementing security controls and evaluating threats. Approves changes to data systems, delegates stewardship tasks, and coordinates between business and technical teams. Promotes cross-functional collaboration, monitors data performance, provides advocacy and training on data governance, and manages resources to ensure robust, secure, and valuable data that supports strategic objectives and innovation. | L10: Challenges: Complexity in Data Governance: Coordinating and implementing consistent governance practices across various data domains can be challenging, leading to fragmented data policies. Data Quality Challenges: Ensuring high data quality and consistency requires constant oversight and access to adequate cleansing resources, which can be resource-intensive. Resistance to Change: Implementing data policies or systems may face resistance from stakeholders resistant to altering established workflows. Compliance and Regulatory Pressure: Keeping up with changing legal and regulatory requirements can be demanding and complex, requiring continuous update and monitoring. Cross-Functional Coordination: Building effective collaboration between technical teams and business units can be difficult, with potential misalignments in goals and communication barriers. Security Threats: Protecting data from security breaches requires ongoing vigilance and investment in new security technologies and practices. Budget Constraints: Limited resources may constrain the implementation of necessary data management improvements and technology upgrades. Integration Issues: Challenges in integrating new data systems with existing infrastructure can lead to inefficiencies or conflicts. Latent Gains: Enhanced Decision-Making: Effective data ownership can lead to improved data-driven decision-making, fostering innovation and strategic advancement. Improved Data Quality: Proactive data management leads to cleaner, more reliable, and higher-quality data, enhancing operational effectiveness. Compliance and Security: Robust data governance helps mitigate risks and ensures compliance with regulatory frameworks, protecting organizational integrity and reputation. Cross-Functional Collaboration: Enhanced alignment between teams improves communication, leading to more cohesive strategies and execution across business and IT functions. Cost Efficiency: Streamlining data processes and eliminating redundancies can lead to operational efficiencies and reduce costs over time. Competitive Advantage: By leveraging data effectively, organizations can gain a competitive edge through better market insights and customer understanding. Innovation Opportunities: Well-managed data opens doors to new opportunities for innovation, product development, and personalized customer experiences. Employee Empowerment: Training initiatives under data ownership can lead to higher data literacy, empowering employees to make informed decisions and contribute to strategic goals. By addressing these issues and pursuing latent gains, a Data Owner can significantly impact the organization's ability to manage data as a strategic asset, turning challenges into opportunities for growth and value creation. | M10: The FAIR principles are key guidelines for improving data management and harnessing the value of data assets. Implementing these principles can bring several potential benefits to an organization through the role of a Data Owner: Potential FAIR Benefits: 1. Findable: Enhanced Discoverability: By implementing standardized metadata and indexing, data becomes easily searchable, enabling stakeholders to quickly locate needed information. Efficient Data Utilization: Improved discoverability reduces time spent searching for data, allowing teams to focus on analysis and decision-making. 2. Accessible: Improved Data Sharing: Ensuring data accessibility through clearly defined protocols allows stakeholders across the organization to seamlessly access data, fostering collaboration. Transparent Permission Structures: Establishing clear data access protocols reduces confusion and enhances security by ensuring only authorized users can access sensitive data. 3. Interoperable: System Compatibility: Interoperable data can integrate across different systems and platforms, reducing silos and increasing data flow across functions. Enhanced Collaboration: It simplifies data collaboration both internally and externally with partners, as data can be easily shared and utilized in a variety of formats without technical barriers. 4. Reusable: Maximized Data Value: Data that is structured for reusability enhances its value by allowing teams to leverage it for multiple analyses and projects beyond its initial purpose. Sustainability: Reusable data facilitates long-term sustainability of data assets, reducing duplication of efforts and promoting efficient use of resources. Overall Benefits: Improved Efficiency and Productivity: By applying the FAIR principles, organizations can streamline data processes and enhance productivity across teams by facilitating easier access and utilization of information. Innovation and Strategic Insight: FAIR-aligned data management supports innovative uses of data, helping organizations develop new insights and strategic advances. Robust Data Governance: The principles reinforce comprehensive data governance, promoting consistency, compliance, and security across data assets. Reduced Costs: Efficient data management practices can reduce redundancies and minimize resource expenditure associated with data handling and storage. Integrating the FAIR principles through the role of a Data Owner can greatly enhance the organization's ability to leverage data assets effectively, turning them into a cornerstone for business growth and transformation. {()} {[( F1, A1, I1, R1.1 )]} – F1 provides general benefit for this role; A1 provides general benefit for this role; I1 provides general benefit for this role; R1.1 provides general benefit for this role. | N10: [GN] Seems to be a duplicate of Business_Owner/ - propose to park or remove (note: clarify which speficic FAIR principles are in scope) | O10: Issues: In a non-FAIR environment, Data Owners face unclear data visibility, inconsistent governance enforcement, poor metadata and lineage, and limited control over data reuse. This increases regulatory, security, and reputational risk, complicates accountability, weakens cross-functional coordination, and makes it difficult to demonstrate compliance, value, and proper stewardship of data assets. Latent Gains: | P10: F1 ensures datasets under ownership are persistently identified, enabling clear accountability and traceability; F2 provides rich metadata that demonstrates the dataset’s purpose, scope, and quality to consumers; A1 guarantees reliable access controls so the owner can manage who uses the dataset; I1 enables interoperability with other organizational datasets, increasing business value; R1.1 assures reproducibility of results generated from the dataset, reinforcing trust in its use; R1.2 provides clarity on reuse through explicit licensing, reducing risks and negotiations for the data owner.
A11: https://github.com/PistoiaAlliance/FAIRMaturityMatrix/blob/FAIR-MM-V1.2/FAIR_personas/Data_Protection_Officer.md | B11: Data_Protection_Officer | C11: Data Enabler | D11: Ensures compliance with privacy, regulatory, and security requirements. | E11: Birgit Meldal | F11: Copilot; https://www.wikidata.org/wiki/Q30682903 | G11: Data Privacy Officer; Data Security Officer | H11: Business_Leader,Data_Owner,Data_Steward | I11: {nice to have/ to complete} | J11: { To review with group - V1.2 } | K11: Ensures that research, clinical, and operational data practices comply with GDPR, HIPAA, and other international regulations. Their tasks include reviewing data governance policies, monitoring cross-border data transfers, and advising R&D and IT teams, e.g. on privacy-by-design practices. They work closely with clinical operations to oversee the lawful use of patient and trial data, ensuring consent and data-use conditions are accurately captured and respected. Conducts regular audits, risk assessments, and staff training to reinforce compliance culture across the organization. Act as the bridge between regulators, business leaders, and scientists, balancing the drive for data sharing and data-driven innovation with the company’s obligations to protect privacy, security, and trust. | L11: risk of data breaches if data management doesn't include security at all levels | M11: Data may be FAIR on paper but cannot be used widely without the right security measures - esp for propriatory and data and data containing – A1.2 guarantees controlled access for privacy compliance; R1.1 ensures reproducible compliance evidence. | N11: (needs better descrpitons) | O11: Issues: risk of data breaches if data management doesn't include security at all levels. Latent gains: implementing FAIR principles would reduce these challenges and unlock efficiency, compliance, and reuse. | P11: A1.2 enforces controlled access for privacy compliance; R1.1 guarantees reproducibility of compliance evidence
A12: https://github.com/PistoiaAlliance/FAIRMaturityMatrix/blob/FAIR-MM-V1.2/FAIR_personas/Data_Scientist.md | B12: Data_Scientist | C12: Data Producer | D12: Data Scientists find, compile, clean, preprocess and analyze complex datasets. They interpret data trends, develop predictive models, and communicate findings to inform strategic decision-making. Data Scientists also design experiments, possess expertise in statistical methods, programming, data visualization, database management, and may have domain-specific knowledge. See also “researcher” . | E12: giovanni nisato | F12: https://pistoiaalliance.github.io/FAIRMaturityMatrix/resources_lexicon | G12: R&D Data Scientist; Computational Scientist; Bioinformatician; Machine Learning Engineer; Quantitative Analyst; Applied Data Scientist; AI/ML Scientist; | H12: Advanced_Data_Analysis_and_Insights_Professional,Citizen_Data_Scientist,Researcher,Data_Analyst,Data_Engineer | I12: Used at: Novartis, GSK | J12: FAIRMM_V1.1 | K12: Performs analysis of R&D and clinical data, integrating diverse sources such as omics datasets (RNAseq, DNAseq, proteomics, metabolomics), digital pathology images, and real-world evidence. Cleans, harmonizes, and preprocesses complex data to ensure quality and consistency. Applies statistical and computational methods to uncover biological mechanisms, identify biomarkers, and support target discovery, patient stratification, and clinical outcome prediction. Collaborates with bioinformaticians, biostatisticians, and domain experts to interpret results and translate findings into actionable insights for drug discovery and development. | L12: Issues: different, inconsistent ontologies and spread out across different sources and sometimes not knowing that they are existing | M12: FAIR data transforms the way research and analysis are conducted. When data is Findable, Accessible, Interoperable, and Reusable, it eliminates one of the greatest barriers to scientific progress—the time lost searching for, cleaning, and reconciling fragmented datasets. FAIR data allows Data Scientists to quickly discover high-quality, well-annotated datasets across R&D, clinical, and real-world domains, accelerating hypothesis generation and model development. Interoperable data formats and shared standards enable seamless integration of diverse data types—from omics and imaging to patient and assay data—allowing deeper, more holistic analyses. Reusable datasets and documented workflows enhance reproducibility, making results easier to validate and build upon. Ultimately, FAIR data empowers Data Scientists to focus less on data wrangling and more on interpreting results, generating insights, and driving data-informed decisions that advance discovery, improve clinical outcomes, and reduce development timelines. | N12: must have | O12: Issues: Issues: different, inconsistent ontologies and spread out across different sources and sometimes not knowing that they are existing. Latent gains: implementing FAIR principles would reduce these challenges and unlock efficiency, compliance, and reuse. | P12: F1 guarantees persistent identifiers to trace datasets across workflows; F2 provides rich metadata that makes datasets discoverable and interpretable; A1 ensures stable access for computational pipelines; I1 supports integration of heterogeneous datasets for machine learning; R1.1 ensures reproducibility of models and analyses across studies
A13: https://github.com/PistoiaAlliance/FAIRMaturityMatrix/blob/FAIR-MM-V1.2/FAIR_personas/Data_Standards_and_Governance_Expert.md | B13: Data_Standards_and_Governance_Expert | C13: Data Enabler | D13: Acts as a governance advisor and facilitator, ensuring the adoption and compliance of data standards across the organization. Provides expertise on data standards and governance within a specific business function. Defines how data is managed, protected, and used across the enterprise by establishing policies, standards, and roles that ensure data is accurate, secure, compliant with regulations, and aligned with business objectives. | E13: giovanni.nisato@pistoiaalliance.org/ Emiliano Reynares | F13: Email communication / FAIR-for-pharma | G13: Policy Maker; Data Governance Lead; Information Governance Manager; Policy Owner | H13: Business_Analyst,Data_Owner,Data_Steward,Researcher | I13: {nice to have/ to complete} | J13: { To review with group - V1.2 } | K13: ensures consistent, compliant, and interoperable data practices across research and manufacturing. Working with scientists and technical teams, the expert defines and maintains controlled vocabularies and standardized term lists for Laboratory Information Management Systems (LIMS) and Manufacturing Execution Systems (MES), ensuring methods, processes, and data are recorded in FAIR-compliant formats before integration into central databases. In production contexts such as tablet manufacturing, the expert applies the ISA-88 (S88) standard to structure and harmonize process data. The role defines and enforces policies for data quality, security, privacy, and usage; assigns ownership and stewardship responsibilities; and ensures compliance with internal standards and external regulations. The expert maintains visibility of data provenance and lineage to ensure traceability and trust, promotes adoption of governance frameworks across business and technical functions, and monitors the effectiveness of data standards to support reliable, reusable, and regulatory-ready information. | L13: The main issues are convincing the scientific departments to put the time in up front to deliver a benefit they can’t directly see. | M13: FAIR principles transforms data governance from a compliance obligation into a strategic enabler of efficiency, quality, and trust. FAIR ensures that data is findable and discoverable across systems, reducing duplication and enabling reuse of validated information. Accessibility allows authorized users to retrieve data seamlessly within compliant frameworks, while interoperability enables consistent data exchange across instruments, laboratories, and business units without loss of meaning—directly supporting harmonization of LIMS, MES, and enterprise data models. Reusability extends the value of high-quality, well-documented data, improving reproducibility, regulatory readiness, and analytics potential. For this expert, FAIR provides a concrete framework to drive standardization, traceability, and continuous improvement, turning governance into a catalyst for innovation and long-term organizational learning. | N13: [GN] - check if must have. / overal with Legal data and ontology experts ? | O13: Issues: Convincing scientists to invest time upfront in structured data capture remains the main hurdle. Benefits of FAIR are not immediately visible, leading to resistance and inconsistent adoption. Metadata entry is seen as extra work; tools and vocabularies remain fragmented across LIMS, MES, and ELN systems. Legacy data, unclear ownership, and competing standards add friction, while governance enforcement and balancing compliance with usability continue to challenge implementation. Latent gains: Once FAIR principles are embedded, data becomes findable, traceable, and reusable across research and manufacturing. Efficiency improves through reduced duplication and faster access to validated information. Compliance and audit readiness strengthen through clear provenance and standardization. Harmonized data flows enable interoperability, AI-driven analytics, and sustained knowledge reuse—turning governance from a control mechanism into a catalyst for scientific productivity and long-term data value. | P13: F1 provides persistent identifiers that governance experts can mandate to ensure data is consistently referenced across the organization; F2 enriches metadata so governance frameworks can require transparency and completeness; A1 guarantees that access protocols are standardized, making governance policies easier to enforce; I1 ensures interoperability across domains, allowing governance rules to scale enterprise-wide; R1.3 promotes reuse of data aligned with recognized community and industry standards, reinforcing organizational compliance and credibility.
A14: https://github.com/PistoiaAlliance/FAIRMaturityMatrix/blob/FAIR-MM-V1.2/FAIR_personas/Data_Steward.md | B14: Data_Steward | C14: Data Enabler | D14: Data stewardship encompasses the set of practices that ensure data is properly collected, stored, maintained, and shared throughout its entire lifecycle. FAIR data stewardship extends traditional data management by introducing a coordinated framework that ensures data is (or becomes) and remains compliant to Findable, Accessible, Interoperable, and Reusable (FAIR) principles. The core responsibilities of a Data Steward vary widely, ranging from policy development and advisory functions to operational, technical, and IT-related activities. These responsibilities may differ across research-performing and data-driven organizations, where job titles and scopes of work may also vary. Data stewardship roles can be coordination-focused, policy-oriented, research-oriented, or infrastructure-oriented, depending on organizational needs and maturity. A Data Steward may also serve as a lead role within a data governance initiative, taking ownership of data assets and collaborating with business and technical stakeholders to define and implement governance objectives. This role is closely linked to maintaining data integrity and control within data governance and master data management frameworks. | E14: giovanni.nisato@pistoiaalliance.org / Kathleen Rand | F14: https://rdmkit.elixir-europe.org/data_steward. https://fairtoolkit.pistoiaalliance.org/methods/data-stewardship/ https://www.gofair.us/data-stewardship | G14: Data Governance Steward; Metadata Steward; Records Steward; Knowledge Scientist | H14: Master_Data_Manager,Reference_Data_Manager,Data_Owner,Data_Protection_Officer,Data_Quality_Manager,Subject_Matter_Expert,Data_Standards_and_Governance_Expert,Data_Integration_Specialist,FAIR_Community_Manager,Curator, Ontologist, | I14: Used at GO-FAIR see also ELIXIR | J14: FAIRMM_V1.1 | K14: A FAIR Data Steward serves as a connector between scientific, regulatory, business, and technical functions, ensuring that data remains accurate, compliant, and aligned with both organizational and FAIR principles. In the pharmaceutical context, the role underpins data integrity and regulatory compliance while enabling data reuse across R&D, manufacturing, and post-market activities for example. The FAIR Data Steward may help define and enforces governance policies, establishe and monitor data quality standards, and ensures that metadata and provenance information are complete, standardized, and persistently linked to underlying datasets. This role requires continuous collaboration with multiple stakeholders. Working closely with the Master Data Manager and Reference Data Manager, the steward ensures harmonized and trusted master and reference data. In partnership with the Data Owner and Data Protection Officer, they clarify accountability and ensure adherence to privacy and data protection regulations. Together with the Data Quality Manager and Subject Matter Experts, they validate data definitions, ensure high-quality standards, and maintain contextual relevance. Coordination with the Data Standards and Governance Expert and the Data Integration Specialist guarantees alignment with enterprise standards and seamless interoperability across systems. Engagement with the FAIR Community Manager, Curator, and Ontologist supports consistent application of semantic models, promotes best practices, and strengthens the organization’s FAIR culture. Through these collaborations, the FAIR Data Steward acts as an integrator who embeds FAIR principles into daily operations, transforming data into a trusted, reusable, and compliant asset. This enables the organization to achieve greater efficiency, regulatory readiness, and scientific and business value throughout the pharmaceutical data lifecycle. They can also act as a link between business and technical teams, ensuring data is accurate, compliant, and aligned with organizational goals. They define governance policies, procedures, and roles, set and maintain data quality rules, monitor KPIs, and resolve issues with relevant stakeholders. They may (alond or inc oordination with other FAIR personas) manage master data to maintain a single source of truth, ensure proper integration and synchronization, and keep metadata and data catalogs accurate and accessible. | L14: Typical issues for a Data Steward include unclear or overlapping role definitions, leading to confusion or gaps in data stewardship and governance. They often struggle with poor data quality and incomplete or inconsistent definitions, which undermine trust and value in organizational data. Cultural resistance—where colleagues see new governance practices as bureaucratic or disruptive—can make adoption challenging. Data stewards must also navigate increasing complexity in regulatory compliance, data security, and integration of new technologies. Finally, many face resource constraints, such as lack of time, training, or effective tools, reducing their overall impac | M14: The adoption of FAIR principles enhances data quality, trust, and discoverability while minimizing duplication of effort. FAIR provides a structured framework. By improving data quality, consistency, and documentation, it rebuilds trust in organizational data and ensures a reliable foundation for analytics and decision-making. FAIR’s emphasis on metadata, accessibility, and interoperability supports stronger compliance with regulatory frameworks, simplifies auditability, and streamlines integration across systems. Moreover, it helps overcome cultural resistance by embedding transparent, value-driven practices that demonstrate efficiency and impact. Ultimately, FAIR empowers Data Stewards to achieve greater operational efficiency, foster collaboration, and enable sustainable data reuse across the organization. | N14: Must have | O14: Issues: Typical issues for a Data Steward include unclear or overlapping role definitions, leading to confusion or gaps in data stewardship and governance. They often struggle with poor data quality and incomplete or inconsistent definitions, which undermine trust and value in organizational data. Cultural resistance—where colleagues see new governance practices as bureaucratic or disruptive—can make adoption challenging. Data stewards must also navigate increasing complexity in regulatory compliance, data security, and integration of new technologies. Finally, many face resource constraints, such as lack of time, training, or effective tools, reducing their overall impac. Latent gains: implementing FAIR principles would reduce these challenges and unlock efficiency, compliance, and reuse. | P14: F1 ensures identifiers to enforce consistent governance; A1 guarantees accessibility for governance workflows; R1.1 enables reproducible governance evidence; R1.3 supports reuse by aligning with community practices | R14: Improve data quality, trust, and discovery while reducing duplication. It strengthens compliance and traceability through clear metadata and audit trails. Interoperability enables seamless integration across systems, boosting collaboration and the value of master data. Reusability ensures data can serve multiple purposes, maximizing long-term value and supporting continuous improvement. F1 ensures clear identifiers for governance; A1 guarantees accessibility in organizational workflows; R1.1 enables reproducible governance processes; R1.3 supports reuse with community-based practices. | S14: A data steward refers to the lead role in a data governance project. Data Stewards take ownership of the data and work with the business to define the programme’s objectives. The role of a Data Steward is specifically tasked with maintaining data control in data governance and master data management initiatives on a day-to-day basis. Data Stewardship is required for data implementation and data management to succeed. An example of what they may do to achieve this is drafting the data quality rules which their data is measured against. | T14: Acts as the key link between business and technical teams, ensuring data is accurate, compliant, and aligned with organizational goals. They define governance policies, procedures, and roles, set and maintain data quality rules, monitor KPIs, and resolve issues with relevant stakeholders. They may (alond or inc oordination with other FAIR personas) manage master data to maintain a single source of truth, ensure proper integration and synchronization, and keep metadata and data catalogs accurate and accessible.
A15: https://github.com/PistoiaAlliance/FAIRMaturityMatrix/blob/FAIR-MM-V1.2/FAIR_personas/Data_Strategy_Owner.md#description-of-fair-benefits-fordata_strategy_owner | B15: Data_Strategy_Owner | C15: Data Enabler | D15: A senior leader responsible for defining, developing, and executing an organization's overarching data strategy to align with business goals. This role translates business strategy into a data strategy, establishing the roadmap for how data will be collected, managed, governed, and leveraged to drive value and innovation across the company. | E15: Birgit Meldal / GN | F15: {Co-pilot generated) | G15: Chief Data Officer (CDO); Chief Analytics Officer (CAO); Head of Data Strategy; Director of Data Strategy; Data Strategy Lead; Data Strategy & Governance Lead | H15: Business_Leader,Business_Analyst,Business_Owner,Project_Manager, Data_Steward | I15: {to complete: worth keeping because it’s not the business owner (see definition and synonyms); it could be the same a business owner for some data but it should be a senior leader such as the CDO or CIO} | J15: { To review with group - V1.2 } | K15: Data Strategy Owners set the strategic vision for how data supports business goals and defines priorities for data initiatives. They ensure data management practices align with organizational objectives, enforce data policies, and are accountable for the quality, security, and compliance of the data. The role involves making key decisions on data usage, resource allocation, and approving access or data sharing agreements. They collaborate with business and technical teams to implement governance, manage risks, and support data-driven decision-making. Continuous oversight of data quality, regulatory adherence, and alignment of data efforts with business strategy are core to their responsibilities{/ to complete} | L15: without a strategy data and related tools may look very useful but may not solve any problems wasting time and money producting them | M15: FAIR benefits are mainly interoperability – ensuring all data are managed to linked/interoperable standards (which makes mapping possible) [if this role doesn’t exist, the consequence are data silos] | N15: [GN] adited FAIR benefits Narrative | O15: Issues: without a strategy data and related tools may look very useful but may not solve any problems wasting time and money producting them. Latent gains: implementing FAIR principles would reduce these challenges and unlock efficiency, compliance, and reuse. [if this role doesn’t exist, the consequence are data silos] | P15: F1 provides persistent identifiers that underpin trustworthy, enterprise-wide data assets for strategic decision making; F2 ensures metadata richness so executives can evaluate the value and readiness of data for business opportunities; A1 guarantees that critical datasets are reliably accessible, enabling agility in responding to market shifts; I1 enables cross-domain interoperability, supporting enterprise-wide analytics and innovation; R1.2 clarifies reuse conditions, allowing leadership to safely unlock data assets for partnerships, monetization, and ecosystem engagement. | R15: Issues: without a strategy data and related tools may look very useful but may not solve any problems wasting time and money producting them. Latent gains: implementing FAIR principles would reduce these challenges and unlock efficiency, compliance, and reuse. [if this role doesn’t exist, the consequence are data silos] | S15: FAIR benefits are mainly interoperability – ensuring all data are managed to linked/interoperable standards (which makes mapping possible) [if this role doesn’t exist, the consequence are data silos]
A16: https://github.com/PistoiaAlliance/FAIRMaturityMatrix/blob/FAIR-MM-V1.2/FAIR_personas/FAIR_Community_Manager.md | B16: FAIR_Community_Manager | C16: Data Enabler | D16: An individual or group responsible for facilitating and managing a community of practice (CoP). The organizer’s role involves coordinating meetings, events, and activities for the community, creating channels for communication and knowledge sharing, and fostering a supportive and inclusive environment where members feel comfortable exchanging ideas and experiences. They may also be involved in recruiting new members, setting goals and objectives for the community, and ensuring that it remains vibrant and relevant to its members’ needs and interests. Person who organizes groups of people around shared aims - see https://the-turing-way.netlify.app/collaboration/research-infrastructure-roles/community-manager.html | E16: giovanni.nisato@pistoiaalliance.org | F16: https://the-turing-way.netlify.app/collaboration/research-infrastructure-roles/community-manager.html https://pistoiaalliance.github.io/FAIRMaturityMatrix/resources_lexicon | G16: Community of Practice Organiser; (FAIR ) Community Lead; FAIR Engagement Manager; FAIR Knowledge Community Lead; FAIR Community Manager | H16: Business_Leader,Clinical_Data_manager,Data_Steward,Knowledge-Enabled_Citizen,Researcher,Subject_Matter_Expert | I16: {nice to have/ to complete} | J16: FAIRMM_V1.1 | K16: A (FAIR) Community Manager in pharma is responsible for building and nurturing a community of practice (CoP) around FAIR data principles, standards, and best practices. Their activities include organizing workshops, webinars, and discussion forums; coordinating cross-functional meetings with data stewards, clinical data managers, scientists, and IT teams; and maintaining communication channels such as mailing lists, Slack/Teams channels, or internal portals. They curate and disseminate knowledge, including FAIR guidelines, metadata standards, and interoperability frameworks. Additionally, they track emerging trends in data management and FAIR adoption, and actively recruit new members to ensure the community reflects diverse roles and perspectives within the organization. | L16: The FAIR Community Manager faces challenges in aligning stakeholders from different departments and skill levels around common FAIR objectives. Large pharma environments often have siloed data systems, heterogeneous standards, and varying levels of FAIR awareness, making it difficult to foster meaningful engagement and knowledge sharing. Capturing and disseminating lessons learned, best practices, and metadata standards in a way that is accessible, actionable, and trusted by the community can also be complex. Moreover, demonstrating the tangible value of FAIR adoption to senior management and ensuring consistent participation across global teams requires both diplomacy and strategic planning. | M16: FAIR principles provide the FAIR Community Manager with a common framework and language to unite teams around shared data practices. By promoting FAIR-aligned processes—such as standardized metadata, provenance tracking, and controlled vocabularies—the manager enables consistent documentation and reliable data reuse across departments. This supports easier dataset discovery, reduced duplication of effort, and improved cross-study analytics. Clear access protocols and governance ensure that information can be securely shared across teams and regions, fostering trust and collaboration. Through visible success stories and demonstrable value—like faster access to insights and enhanced compliance—the FAIR Community Manager strengthens engagement, accelerates learning, and cultivates a company-wide culture of openness, innovation, and continuous improvement in data management. | N16: merged with "Community Manager". | O16: Issues: The FAIR Community Manager faces challenges in aligning stakeholders from different departments and skill levels around common FAIR objectives. Large pharma environments often have siloed data systems, heterogeneous standards, and varying levels of FAIR awareness, making it difficult to foster meaningful engagement and knowledge sharing. Capturing and disseminating lessons learned, best practices, and metadata standards in a way that is accessible, actionable, and trusted by the community can also be complex. Moreover, demonstrating the tangible value of FAIR adoption to senior management and ensuring consistent participation across global teams requires both diplomacy and strategic planning.. Latent gains: implementing FAIR principles would reduce these challenges and unlock efficiency, compliance, and reuse. | P16: F1 ensures community resources are persistently identified, so members can reliably reference and share them; F2 enriches metadata for community outputs, making them easier to discover and adopt; A1 guarantees accessible communication channels, shared repositories, and training materials; I1 enables interoperability between contributions from different groups, fostering collaboration; R1.3 promotes reuse of outputs that align with community and industry standards, amplifying their impact.
A17: https://github.com/PistoiaAlliance/FAIRMaturityMatrix/blob/FAIR-MM-V1.2/FAIR_personas/FAIR_Trainer.md | B17: FAIR_Trainer | C17: Data Enabler | D17: Trainers design and deliver training programs to a variety of stakeholders ranging from researchers to business leaders and project teams across organisation functions (R&ED, but also development, clinical, franchises), with a focus on awareness and best practice implementation of FAIR data principles. The role supports compliance with corporate data governance policies, regulatory expectations, and scientific needs. It interfaces and interacts woth | E17: giovanni nisato | F17: adapted from: https://rdmkit.elixir-europe.org/trainer | G17: FAIR Educator; FAIR Enablement Specialist; Data Stewardship Instructor | H17: Business_Analyst,Citized_Data_Scientist,Data_Analyst,Data_Steward,Researcher | J17: { To review with group - V1.2 } | K17: Collaborate with data governance leads, technology leads, data architects, community managers and researcher teams to identify training needs aligned with corporate strategy; design tailored, role-specific training schedules; create high-quality, compliant, and FAIR-aligned learning materials (presentations, manuals, e-learning modules, job aids); deliver in-person, virtual, and hybrid sessions combining policy awareness with hands-on skills; promote company-approved and community recommended tools, standards, and workflows; adapt delivery for varied therapeutic areas, modalities, and stages of development (R&D, etc); establish continuous improvement processes through structured feedback and impact measurement. Keep track of FAIR training offering outside of the organisation. | L17: The lower the organisation FAIR maturity level, the higher the complexity of the role and the need to create awareness. Lack of clarity and alignment in terms of needs and requirements from the organisations can be expected. At more advanced maturity levels, traning may become diversified and tuned to the needs of differen stakeholders, from business leaders, to researchers, to Data Stewards and Architects. In a change management process, the value of the training, FAIR and data-centric approach may be challenged. | M17: FAIR principles provide a strong foundation for trainers to embed best practices in data management and reusability across teams and organizations. By leveraging success stories, FAIR Trainers can effectively articulate the underlying rationale ('why') for FAIR training, fostering greater engagement and commitment. The re-use of FAIR-aligned training materials and the adoption of open standards are facilitated by highlighting real-world examples from FAIR implementation journeys and profiles. With well-defined metrics and frameworks such as FAIR indicators and the FAIR Maturity Model (FAIR MM), Trainers are able to assess both datasets and organizational adherence, offering tangible benchmarks for progress. The impact of training is ultimately heightened through the availability of FAIR-compliant data and implementation examples | N17: must have | O17: Issues: The lower the organisation FAIR maturity level, the higher the complexity of the role and the need to create awareness. Lack of clarity and alignment in terms of needs and requirements from the organisations can be expected. At more advanced maturity levels, traning may become diversified and tuned to the needs of differen stakeholders, from business leaders, to researchers, to Data Stewards and Architects. In a change management process, the value of the training, FAIR and data-centric approach may be challenged.. Latent gains: implementing FAIR principles would reduce these challenges and unlock efficiency, compliance, and reuse. | P17: F2 provides richly described training datasets for learners; R1.3 promotes reuse of materials aligned with community standards | T17: [RS]: FAIR principles provide a strong foundation for trainers to embed best practices in data management and reusability across teams and organizations. By leveraging success stories, FAIR Trainers can effectively articulate the underlying rationale ('why') for FAIR training, fostering greater engagement and commitment. The re-use of FAIR-aligned training materials and the adoption of open standards are facilitated by highlighting real-world examples from FAIR implementation journeys and profiles. With well-defined metrics and frameworks such as FAIR indicators and the FAIR Maturity Model (FAIR MM), Trainers are able to assess both datasets and organizational adherence, offering tangible benchmarks for progress. The impact of training is ultimately heightened through the availability of FAIR-compliant data and implementation examples—F2 provides richly described cases for instructional use, while R1.3 ensures materials remain reusable and aligned with recognized community standards. Altogether, this accelerates learning, builds trust, and cultivates a culture of openness, innovation, and continuous improvement. Benefit from success stories to articulate the "why" of the training. Ability to re-use FAIR training materials. Ability to use open standards, showcase examples from FAIR implementation journeys and FAIR implementation profiles. Benefit from clearer metrics and frameworks to assess FAIR data sets (FAIR indicators) and organisations. (FAIR MM). Higher impact of training due to availability of FAIR compliant data and examples of implementation. {()} {[( F2, R1.3 )]} – F2 provides richly described examples for training materials; R1.3 ensures reuse of materials aligned with community standards.
A18: https://github.com/PistoiaAlliance/FAIRMaturityMatrix/blob/FAIR-MM-V1.2/FAIR_personas/Lab_manager.md | B18: Lab_Manager | C18: Data Consumer | D18: Oversees the daily operation of research or testing laboratories, ensuring that experiments, equipment, personnel, and data workflows run efficiently, safely, and in compliance with regulatory and quality standards. They coordinate between scientists, data teams, and quality or regulatory functions to maintain accurate experimental records, ensure data integrity, and optimize resource utilization. The role combines scientific leadership with operational and digital oversight, increasingly relying on data-driven decision-making to improve productivity and reproducibility. The role may include a wide range of responsibilities, including budget and spends, overseeing daily operations, ensuring safety, managing lab and IT equipments and supplies, and supervising staff. | E18: John Apathy, Debashree Chakrabarti / GN | F18: https://en.wikipedia.org/wiki/Laboratory_manager | G18: Laboratory Operations Manager; Research Operations Manager; Laboratory Coordinator; Facility Manager; Laboratory Supervisor; Laboratory Operations Lead; Lab Head, Principal investigator; | H18: Data_Owner,Lab_Manager,Project_Manager,Researcher,Business_Owner | I18: Used at Abbvie (unofficial title) | J18: { To review with group - V1.2 } | K18: Manage day-to-day activities, ensuring experiments, workflows, and safety procedures run smoothly and comply with regulatory standards. Manage data workflows and documentation, including the capture, validation, and archiving of experimental data across digital systems (e.g., ELN, LIMS) to maintain integrity, traceability, and reproducibility. Allocate staff, instruments, and materials effectively to maximize productivity and minimize delays or downtime. Ensure quality, compliance, and audit readiness, including monitor data quality, equipment calibration, and documentation to meet GxP and regulatory requirements, supporting internal and external audits. | L18: 1. Assumption that managing digital assets is an IT task and therefore often neglected 2. Lack of training towards FAIR practices 3. Often use old applications due to some legacy automation 4. Do not account for funds for digital asset upkeep or understand security policies 5. The role often rotates within a lab (sort of an additional responsibility) | M18: transforms laboratory operations from manual and fragmented to digital, efficient, and compliant. By making experimental data findable through persistent identifiers and standardized metadata, FAIR ensures that samples, assays, and results can be quickly located, linked, and reused across projects—saving time and reducing administrative overhead. Accessible and well-governed data enable seamless sharing between teams and systems, improving collaboration while maintaining security and regulatory control. Through interoperable data formats and shared ontologies, FAIR connects instruments, ELNs, LIMS, and analytical platforms, eliminating silos and streamlining workflows. Finally, reusable, provenance-rich data strengthen reproducibility and audit readiness, allowing the Lab Manager to demonstrate data integrity and compliance effortlessly. In a FAIR-mature environment, the Lab Manager can shift focus from operational firefighting to continuous improvement, driving higher quality, efficiency, and scientific innovation across the laboratory ecosystem. | N18: must have | O18: Issues: Lab Managers often face fragmented and inefficient data environments, where managing digital assets is seen as an IT responsibility rather than an integral part of laboratory operations. Limited training in FAIR data practices and data governance leads to inconsistent documentation and poor metadata quality. Legacy applications and automation systems constrain interoperability and hinder modernization efforts. Budget planning rarely accounts for the upkeep of digital assets or data infrastructure, resulting in technical debt and security vulnerabilities. Moreover, the role of Lab Manager may rotate among staff, leading to inconsistent ownership, variable data management standards, and loss of institutional knowledge. Latent Gains: Implementing FAIR principles transforms lab management by embedding data stewardship directly into operational workflows. FAIR ensures structured metadata, standardized formats, and interoperable systems that enhance traceability, compliance, and reproducibility. Automated data capture and integration reduce manual workload, freeing managers to focus on quality and innovation. Training and clear governance frameworks empower lab personnel to maintain digital assets responsibly, while better budgeting for data infrastructure ensures sustainability. Ultimately, FAIR enables a transparent, efficient, and future-ready lab environment that supports continuous improvement and scientific excellence. | P18: F1 provides persistent identifiers that track samples, instruments, and experimental outputs unambiguously; F2 ensures metadata is complete so lab operations, methods, and results are transparent and auditable; A1 guarantees secure yet efficient access to lab data across instruments and IT systems; I1 enables interoperability between laboratory information systems and research platforms; R1.1 assures reproducibility of experiments and regulatory submissions, reducing compliance risks.
A19: https://github.com/PistoiaAlliance/FAIRMaturityMatrix/blob/FAIR-MM-V1.2/FAIR_personas/Master_Data_Manager.md | B19: Master_Data_Manager | C19: Data Enabler | D19: Role ensuring authoritative single sources of truth across the enterprise (e.g., products, customers, materials). Manages the master data in a given business domain. Responsible for managing vocabularies, code lists, and ontologies to ensure consistency and semantic alignment. Manages reference data to ensure master data from multiple sources are aligned. An Enterprise Data Steward manages and enforces data governance policies at an enterprise level, bridging the gap between business users, data owners, and IT. They ensure that enterprise-wide data assets are properly defined, cataloged, and maintained. | E19: Avinash Dixit/ GN / Nick Lynch | F19: https://www.gartner.com/en/data-analytics/topics/master-data-management https://en.wikipedia.org/wiki/Master_data_management | G19: Enterprise Data Manager; Data Domain Manager; Master Data Lead; Master Data Steward; Master Data Coordinator; Reference Data Manager; Enterprise Data Steward | H19: Business_Owner,Curator,Lab_Manager,Project_Manager,FAIR_Data_Architect,Data_Steward | J19: { To review with group - V1.2 } | K19: Define and maintain enterprise master data standards; oversee creation, quality, and governance of master data domains (e.g., products, customers, materials); ensure harmonization and alignment across business units and IT systems; resolve data ownership conflicts and redundancies; collaborate with Data Stewards, Architects, and Analysts to embed FAIR principles into master data processes; monitor data quality KPIs and enforce remediation workflows; support regulatory reporting and compliance through accurate, consistent master data. Owns the consistency, versioning, and controlled distribution of reference data across the enterprise Catalogue domains, owners, schemas, hierarchies, valid values. Define governance (RACI), versioning, and change workflows. Build/maintain crosswalk, publish via APIs Run DQ checks, monitor SLAs, communicate releases Maintain audit trails, lineage, and documentation | L19: Issues: duplicated and inconsistent master data across business units; lack of persistent identifiers creates ambiguity in reporting; poor metadata prevents discovery of authoritative records; siloed systems hinder integration and interoperability; unclear ownership slows resolution of data quality issues; regulatory submissions are delayed or error-prone due to conflicting datasets. Latent gains if FAIR adopted: F1 enables persistent identifiers that define single sources of truth; F2-rich metadata supports discoverability and governance; A1 provides secure yet consistent access across systems; I1/I2 ensure interoperability between domains and applications; R1.1/R1.2 guarantee reproducible, licensed reuse of master data, reducing compliance risk and speeding reporting.]} | M19: FAIR principles ensures authoritative, high-quality master and reference data consistently aligned across systems and business domains. FAIR makes master data findable through persistent identifiers and rich metadata, accessible via governed and auditable access points, interoperable through shared vocabularies and ontologies, and reusable thanks to embedded provenance and usage context. This foundation drives data democratization, empowering stakeholders across the enterprise with trusted, well-documented data assets, while supporting AI readiness through standardized, machine-actionable metadata. FAIR also strengthens regulatory compliance by ensuring that master data are fully traceable, governed, and reusable, reducing risk and improving auditability. Ultimately, FAIR maturity transforms data stewardship from an operational task into a strategic enabler of enterprise efficiency, data trust, and cross-domain interoperability. | N19: Combined with Reference Data Manager | O19: Issues: duplicated and inconsistent master data across business units; lack of persistent identifiers creates ambiguity in reporting; poor metadata prevents discovery of authoritative records; siloed systems hinder integration and interoperability; unclear ownership slows resolution of data quality issues; regulatory submissions are delayed or error-prone due to conflicting datasets; uncontrolled code list/version drift breaks integrations; missing lineage/provenance blocks auditability and impact analysis; manual crosswalks between vocabularies are fragile and not reusable; shadow MDMs emerge due to slow or ungoverned access; inconsistent deprecation/change notifications cause downstream breakage; limited API/access standards create friction for data consumers; mistrust in KPIs and AI models due to low-quality master data. Latent gains if FAIR adopted: authoritative and uniquely identified master data provide a single source of truth across systems; standardized, well-described metadata improves discoverability, governance, and cross-domain alignment; secure and harmonized access protocols enable seamless data exchange while preserving control; shared vocabularies and ontologies eliminate semantic ambiguity and make integrations durable; rich provenance, lineage, and licensing information ensure auditability, trust, and regulatory readiness; reusable reference data and automated conformance checks reduce maintenance costs and speed up reporting; harmonized master data accelerates AI and analytics use cases, enhances data democratization, and builds confidence in enterprise-wide data-driven decision-making. | P19: F1 ensures authoritative entities (e.g., products, customers) have persistent identifiers, preventing duplication and ambiguity across systems; F2 provides rich metadata that defines business meaning, lineage, and ownership of master data; A1 guarantees secure but consistent access to authoritative master data across business units; I1/I2 enable interoperability and automated synchronization between enterprise systems; R1.1 assures reproducibility of reports and compliance filings that depend on master data; R1.2 clarifies reuse conditions, allowing trusted sharing of master data across internal and external stakeholders. | R19: data from multiple sources can be combined in metanalyses; data becomes FAIR | S19: Data democratization , supports AI readiness. It strengthens regulatory compliance by ensuring traceable, governed, and reusable master data.
A20: https://github.com/PistoiaAlliance/FAIRMaturityMatrix/blob/FAIR-MM-V1.2/FAIR_personas/Ontologist.md | B20: Ontologist | C20: Data Enabler | D20: An expert in knowledge representation and ontology building, | E20: giovanni.nisato@pistoiaalliance.org/ Kathleen Rand/Philippe Rocca-Serra | F20: https://pistoiaalliance.github.io/FAIRMaturityMatrix/resources_lexicon | G20: Knowledge Engineer; Information Architect; Semantic Data Modeler; Taxonomist; Data Standards Specialist | H20: FAIR_Data_Architect,Curator,Data_Standards_and_Governance_Expert,Reference_Data_Manager | I20: commonly used | J20: FAIRMM_V1.1 | K20: An Ontologist plays a pivotal role in defining and structuring the semantic foundations of an organization’s data ecosystem. Their work involves knowledge elicitation to capture domain expertise and domain modeling to formalize concepts, relationships, and constraints within a specific area. Through knowledge representation and engineering, they transform complex information into actionable, machine-readable models aligned with semantic web standards and technologies. Ontologists actively engage with communities to foster collaboration, build consensus, and promote best practices for interoperability and data reuse. They contribute to the development of industry standards and ensure the quality and consistency of AI-generated semantic representations. By bridging technical precision with organizational needs, the ontologist enables a data-centric approach that enhances understanding, integration, and innovation across systems and disciplines. | L20: 1.challenges of convincing of changing ways of working / change to organization / interaction with information architects classicly training with ER modeling. 2. shortage in trained experts 3. different school of thoughts for ontology development (detrimental to interoperability) 4. can not guarantee out of the box interoperability (no panacea, semantic models can be in conflit and compete) | M20: the application of FAIR principles enhances the creation and maintenance of high-quality, interoperable data models that underpin a data-centric approach. FAIR enables the development of actionable ontological frameworks that drive consistency, reusability, and semantic clarity across the organization. It supports the precise definition of standards and shared understanding of “what good looks like,” ensuring that data models are transparent, well-structured, and aligned with business and scientific objectives. By fostering clarity about model intent and commitment, FAIR empowers ontologists to build trusted, sustainable data ecosystems that facilitate integration, automation, and informed decision-making. | O20: Issues: Ontologists often face the challenge of driving organizational change and convincing teams—particularly those accustomed to traditional information architecture and ER modeling—to adopt new, semantic approaches. There is a persistent shortage of trained experts, and differing schools of thought in ontology development can hinder consistency and interoperability. Moreover, semantic models cannot guarantee seamless interoperability out of the box, as conflicting or competing models may arise across domains. Latent gains: Implementing FAIR principles helps mitigate these challenges by promoting shared standards, improving semantic alignment, and fostering collaboration across disciplines. This approach enhances efficiency, compliance, and data reuse while supporting the gradual transition toward a unified, interoperable, and sustainable data ecosystem. | P20: I1 ensures semantic interoperability across ontologies and vocabularies; I2 enables automated reasoning over structured knowledge; R1.3 promotes reuse of ontologies by aligning with community standards | R20: {nice to have/ to complete} 1. enabling data centricity approach 2. provisioning of actionable models 3. definition of what good looks like 4. clarity about model commitment {()} {[( I1, I2, R1.3 )]} – I1 ensures semantic interoperability of knowledge models; I2 fosters automated reasoning across datasets; R1.3 promotes reuse with community ontology standards. | S20: Issues: 1.challenges of convincing of changing ways of working / change to organization / interaction with information architects classicly training with ER modeling. 2. shortage in trained experts 3. different school of thoughts for ontology development (detrimental to interoperability) 4. can not guarantee out of the box interoperability (no panacea, semantic models can be in conflit and compete). Latent gains: implementing FAIR principles would reduce these challenges and unlock efficiency, compliance, and reuse.
A21: https://github.com/PistoiaAlliance/FAIRMaturityMatrix/blob/FAIR-MM-V1.2/FAIR_personas/Project_Manager.md | B21: Project_Manager | C21: Data Consumer | D21: Coordinates -cross-functional- efforts to deliver projects or initiative on time, within budget, and in compliance with regulatory standards. They oversee projects in -or spanning- research, clinical development, manufacturing, regulatory submissions, and commercialization domains. Acting as the connective link between scientific, operational, and business teams, the Project Manager ensures alignment of objectives, resources, and timelines , including across the drug development lifecycle. They manage risk, track milestones, and facilitate decision-making through clear reporting and proactive issue resolution. In addition, they drive collaboration among internal teams, external partners, and vendors while ensuring adherence to GxP and quality standards. | E21: Ranu Sharma / AD/ GN | F21: https://www.wikidata.org/wiki/Q2552738 | G21: Portfolio Manager; Program Manager; Program Lead; Clinical Project Manager; Project Lead; Project Coordinator; Delivery Manager; Principal investigator; | H21: FAIR_Community_Manager,FAIR_Data_Architect,Business_Owner,Clinical_Data_Manager,Data_Engineer,Data_Owner,Lab_Manager,Project_Manager,Technology_Leader | I21: Used at AbbVie | J21: { To review with group - V1.2 } | K21: Responsible for planning, coordinating, and overseeing projects. Their tasks include defining project scope, timelines, budgets, and deliverables; tracking progress; managing risks and dependencies; and ensuring alignment with business objectives and regulatory requirements. They organize meetings, produce status reports, formulate options for decision makers, and act as the bridge between technical teams, leadership, and stakeholders. | L21: Face challenges in orchestrating FAIR data implementation due to the complexity and heterogeneity of organizational data, multiple stakeholders with varying priorities, and legacy systems resistant to change. They must balance technical feasibility, resource availability, timelines, and compliance requirements while ensuring teams understand and adopt FAIR practices. Communicating the benefits and ROI of FAIR adoption to senior leadership and maintaining engagement across diverse departments can also be challenging, particularly in large global pharma organizations. | M21: For a Project Manager, the implementation of FAIR principles delivers benefits in efficiency, coordination, and project quality. By ensuring that data is findable, accessible, interoperable, and reusable, FAIR provides a structured framework that simplifies planning, execution, and oversight. It enables more predictable project outcomes by making data discoverable and usable from the outset, reducing delays caused by integration, validation, or quality issues. Reusable, high-quality data accelerates timelines, minimizes duplication of effort, and ensures consistent compliance with organizational and regulatory standards. FAIR practices also strengthen collaboration across cross-functional teams by improving transparency, traceability, and alignment of deliverables. For project managers, this translates into more reliable data-driven workflows, streamlined communication, and greater confidence in achieving project objectives efficiently and sustainably. | O21: Issues: struggle with fragmented information scattered across silos, making it difficult to track progress, dependencies, and deliverables efficiently. Inconsistent or incomplete data across R&D, clinical, and regulatory systems causes delays in reporting and decision-making, while limited visibility and traceability often result in duplicated work, misaligned timelines, and poor impact assessment. Manual data consolidation consumes valuable time that could be spent on strategic coordination and risk management. Additionally, poor interoperability between tools and vendors increases rework, handover errors, and operational costs. The lack of standardized metadata and provenance also heightens regulatory and audit risks, as documentation remains inconsistent and incomplete. Latent gains: By implementing FAIR principles, these challenges can be transformed into strategic advantages. Real-time visibility of project data across domains enables proactive monitoring and faster decision-making. Standardized, interoperable data structures streamline collaboration across teams and vendors, while automated reporting replaces manual tracking, improving both accuracy and efficiency. Traceable, reusable data strengthen compliance readiness and reduce audit burden. Clear data ownership and reduced redundancy optimize resource allocation and project planning, while predictive insights from high-quality, integrated data enhance risk management and support strategic portfolio prioritization across the entire drug development lifecycle. | P21: F1: Enables unified tracking of project data through persistent identifiers, reducing duplication and confusion; F2: Provides rich metadata that clarify context, improving communication and coordination across teams; F4: Centralizes data in searchable repositories, giving real-time visibility into project status and dependencies; A1: Ensures standardized access to validated data, streamlining reporting and decision-making; I1: Promotes seamless data exchange between systems, reducing manual consolidation and integration delays; I2: Aligns terminology and metrics through shared vocabularies, ensuring consistent understanding across functions; R1: Delivers high-quality, complete data that can be confidently reused for planning, forecasting, and analytics; R1.2: Provides traceable provenance, strengthening compliance and audit readiness; R1.3: Aligns data with regulatory and community standards (e.g., CDISC, IDMP), accelerating submissions and validation. | R21: facilitates the FAIR data implementation by coordinating cross-functional teams to establish processes that ensure data is findable, accessible, interoperable, and reusable. They manage project timelines and resources to align data management activities with organizational objectives and compliance standards. FAIR data provides frameworks that simplify planning and execution. It creates more predictable project outcomes by ensuring data is discoverable, and usable from the start. Reusable, high-quality data reduces the effort needed for integration, validation, and quality assurance, accelerating project timelines. FAIR practices also enable better collaboration across teams, improve transparency and traceability of project deliverables, and support regulatory and business objectives by ensuring data is reliable, accessible, and ready for analytics, reporting, or secondary use. • Findable (F1–F4): Standardized metadata and persistent identifiers make project datasets easy to locate, track, and monitor progress across multiple teams and systems. • Accessible (A1–A2): Clear access protocols and persistence policies ensure that authorized team members can reliably retrieve data and associated metadata throughout the project lifecycle. • Interoperable (I1–I3): Standardized formats, controlled vocabularies, and ontologies facilitate seamless integration of datasets from diverse sources, enabling cross-team collaboration and reducing dependency delays. • Reusable (R1–R1.3): Provenance documentation, usage licenses, and quality standards allow project deliverables to be reused in future studies, regulatory submissions, or organizational analytics, reducing duplication and improving efficiency.
A22: https://github.com/PistoiaAlliance/FAIRMaturityMatrix/blob/FAIR-MM-V1.2/FAIR_personas/Reference_Data_Manager.md | B22: Reference_Data_Manager | C22: Data Enabler | D22: Responsible for managing vocabularies, code lists, and ontologies to ensure consistency and semantic alignment. Manages reference data to ensure master data from multiple sources are aligned. [RS] A Reference Data Manager is responsible for overseeing the management, quality, and governance of reference data within an organization. This role ensures that reference data (such as codes, classifications, and standard lists) is accurate, consistent, and aligned with business needs. The Reference Data Manager defines data standards, maintains master/reference data sets, monitors data quality, and implements processes that ensure data is FAIR. They collaborate with business units, data stewards, and technology teams to support data governance, resolve data issues, and enable reliable analytics and reporting. | E22: Birgit/ Avinash | F22: https://cio-wiki.org/wiki/Reference_Data_Management_%28RDM%29 | G22: Information Steward, Master Data Manager, Data Steward, Data Governance Lead, Metadata Manager, Data Quality Manager, Data Custodian. | H22: Business_Owner,Curator,Lab_Manager,Ontologist,Project_Manager | I22: used at Pfizer | J22: { To review with group - V1.2 } | K22: Owns the consistency, versioning, and controlled distribution of reference data across the enterprise Catalogue domains, owners, schemas, hierarchies, valid values Define governance (RACI), versioning, and change workflows Build/maintain crosswalk, publish via APIs Run DQ checks, monitor SLAs, communicate releases Maintain audit trails, lineage, and documentation | L22: [RS]: Issues for a Reference Data Manager often include fragmentation of reference data across systems, leading to inconsistencies and frequent manual reconciliation. Lack of standardization results in duplicated or conflicting codes and classifications, which hinders integration and reporting. Poor data provenance and incomplete documentation increase regulatory and audit risks, while limited interoperability slows down system upgrades and business transformations. Additionally, insufficient collaboration between business units and IT can cause misalignment in reference data policies and processes. Latent gains: By applying FAIR principles, the Reference Data Manager can establish unified, well-documented reference data sets that are findable and reusable across the enterprise. Improved data standardization enhances integration, reduces errors, and supports compliant reporting. Real-time access to quality-assured reference data speeds up onboarding of new systems and partners, while strong interoperability enables scalable automation and analytics. Efficient governance reduces effort spent on manual fixes, strengthens audit readiness, and unlocks value for downstream consumers by enabling trusted insights and seamless collaboration. | M22: Data can be mastered which makes it FAIR. Essential for interoperability {()} {[( F1, A1, I1, R1.1 )]} – F1 provides general benefit for this role; A1 provides general benefit for this role; I1 provides general benefit for this role; R1.1 provides general benefit for this role. | N22: [GN] combined with Master_Data_Manager / | O22: Issues: Data cannot be mastered without it having been aligned to standardised reference data resources. Duplicated/competing code lists across applications Manual, ticket-based updates and brittle point-to-point feeds Slow approvals and unclear ownership Breakages after schema/value changes. Latent gains: implementing FAIR principles would reduce these challenges and unlock efficiency, compliance, and reuse. | P22: F1 ensures that reference codes, vocabularies, and ontology terms are persistently identified, avoiding duplication and ambiguity; F2 provides rich metadata that documents definitions, hierarchies, and context of reference data and ontologies; A1 guarantees that reference datasets and ontologies are reliably accessible across the enterprise; I1 enables semantic interoperability, allowing ontologies and code lists to be consistently applied across systems and domains; R1.3 promotes reuse of community-aligned reference standards and ontologies, ensuring compliance and cross-industry compatibility.
A23: https://github.com/PistoiaAlliance/FAIRMaturityMatrix/blob/FAIR-MM-V1.2/FAIR_personas/Researcher.md | B23: Researcher | C23: Data Producer | D23: A person engaged in conducting research, possibly recognized as an occupation by a formal job title. While a researchers produces and uses data, they are not necessarily data scientists (see: data scientist). | E23: Debashree Chakrabarti/ Giovanni Nisato | F23: https://pistoiaalliance.github.io/FAIRMaturityMatrix/resources_lexicon | G23: Investigator; Principal investigator; Scientist 1; Senior Scientist 1 | H23: Citizen_Data_Scientist,Data_Scientist,Data_Steward,Lab_manager,Project_Manager,Subject_Matter_Expert | I23: Used at Abbvie See also: RDM kit: https://rdmkit.elixir-europe.org/researcher | J23: FAIRMM_V1.1 | K23: Researchers advance scientific knowledge in public or private organizations by conducting complex experiments that can generate large amounts of data. They design, perform, reproduce experimental studies, collect and analyse results. They publish their results in peer-reviewed journals, private reports, and knowledge management systems. Researchers use a mix of unstructured formats such as PowerPoint, Excel, and Word, alongside structured systems like LIMS, internal databases, and ELNs. They often develop and use domain-specific abbreviations that may not be widely understood outside their immediate teams. Researchers actively seek advanced tools such as knowledge graphs, AI-powered insights, and new technologies to enhance discovery. However, their focus on scientific inquiry can sometimes lead to gaps in data management practices, such as limited coordination with IT for large data handling or storage optimization. | L23: There is currently no agreed standard practice for scientific documentation. Chemists, molecular biologists, in vivo scientists, and others—from junior interns to senior researchers—each follow different approaches to data governance, with no unified guidance on how various data types should be managed. Ensuring that electronic lab notebooks (ELNs) are legible remains challenging, as critical information is often hidden in truncated spreadsheets or scattered through acronyms stored elsewhere. Additionally, the use of encrypted or vendor-locked file types limits open access and prevents efficient parsing or reuse of valuable research data. | M23: FAIR data principles streamline the research lifecycle from data creation to knowledge sharing. Enhanced metadata makes datasets easier to locate and assess for relevance, while reliable access ensures seamless collaboration across projects. Interoperability connects results across disciplines, fostering integrative discoveries. Alignment with community standards further promotes data reuse, reducing redundancy and supporting transparency. By embedding FAIR practices early—through standardized tools, ontologies, and interoperable systems—researchers can minimize downstream cleanup, improve data quality, and accelerate innovation across the scientific ecosystem. | N23: must have | O23: Issues: There is currently no agreed standard practice for scientific documentation. Different roles—chemists, molecular biologists, in vivo scientists, and others from junior interns to senior researchers—apply diverse and inconsistent approaches to data governance, with no shared guidance on how specific data types should be managed. Electronic lab notebooks (ELNs) often lack clarity, as important details are buried in truncated spreadsheets or hidden behind undefined acronyms. Moreover, the prevalence of encrypted or vendor-locked file types restricts open access, hindering data parsing, interoperability, and reuse. Latent Gains: Establishing common documentation standards and adopting interoperable, FAIR-aligned practices would streamline data management across disciplines. Legible and well-structured ELNs would enhance data discoverability and reuse, while open, accessible file formats would enable seamless information exchange and integration. These improvements would not only reduce data loss and duplication but also accelerate scientific insight, collaboration, and regulatory readiness. | P23: F2 makes datasets easier to locate and assess for research relevance; A1 ensures reliable access to collaborative project data; I1 allows linking results across domains and disciplines; R1.3 promotes reuse by aligning outputs with community standards
A24: https://github.com/PistoiaAlliance/FAIRMaturityMatrix/blob/FAIR-MM-V1.2/FAIR_personas/Subject_Matter_Expert.md | B24: Subject_Matter_Expert | C24: Data Producer | D24: Deep domain expert who consumes and validates FAIR data rather than managing it. A subject matter expert (SME) is a person with deep domain knowledge, often as a practitioner of the area of knowledge. SME are often consulted by knowledge engineers and ontologists in what is known as ‘knowledge elicitation exercice’ to express use cases and concepts which are then organized and modeled in semantic artifact by knowledge engineers. (NB: SME also stands for Small to Medium Enterprise). | E24: giovanni.nisato@pistoiaalliance.org / ⁠Sharma, Ranu | F24: https://pistoiaalliance.github.io/FAIRMaturityMatrix/resources_lexicon | G24: Domain Specialist; Key Opinion Leader; Technical Advisor; Resource Person; Thought Leader; Principal Investigator | H24: Business_Analyst,Data_Steward,Project_Manager,Researcher | I24: {nice to have/ to complete} | J24: FAIRMM_V1.1 | K24: The Subject Matter Expert contributes specialized knowledge and insights within their domain to guide decision-making and solve complex problems. They create and validate technical content and documentation, ensuring accuracy and relevance across projects. In addition, they play a key role in training and mentoring team members and stakeholders, fostering knowledge transfer and capability development. By continuously staying informed about emerging trends and industry developments, they maintain and advance their expertise to support organizational goals and innovation. | L24: 1. Locating relevant data efficiently can be difficult due to the vast amount of information available and potential lack of proper indexing or metadata. 2. Gaining access to necessary data can be hindered by restrictions, lack of interoperability between systems, or inadequate data sharing policies. 3. Integrating data from various sources may be challenging due to differing formats, standards, or terminologies 4. Ensuring data is well-documented, consistently formatted, and contextually rich | M24: FAIR data enhances an SME's ability to efficiently discover, access, and integrate diverse datasets, leading to more informed decision-making and comprehensive insights. It also promotes the sustainable reuse of data, maximizing productivity and driving better business outcomes by ensuring data is well-documented and contextually rich. | N24: must have | O24: Issues: Locating relevant data efficiently is often difficult due to the vast amount of available information and insufficient indexing or metadata. Access to necessary data may be restricted by limited interoperability, inadequate sharing policies, or technical barriers between systems. Integrating data from multiple sources can be challenging when formats, standards, or terminologies differ, and ensuring that data is well-documented, consistently structured, and contextually meaningful remains a persistent obstacle. Latent gains: Implementing FAIR principles would mitigate these challenges by improving data discoverability, accessibility, and interoperability, thereby unlocking greater efficiency, compliance, and opportunities for data reuse and scientific discovery. | P24: F1 ensures that datasets and knowledge objects they consult are persistently identified, so scientific references remain unambiguous; F2 provides rich metadata that gives SMEs the context needed to assess the reliability and applicability of data; A1 guarantees seamless access to trusted datasets, enabling efficient validation and decision support; I1 allows integration of FAIR datasets with their domain expertise, making cross-disciplinary insights possible; R1.1 ensures reproducibility of findings, so SMEs can validate results confidently and build upon them. | R24: 1. Provides specialized knowledge and insights in their domain. 2. Informs decision-making and problem-solving. 3. Creates and validates content and technical documents. 4. Trains and mentors team members and stakeholders. 5. Stays updated on industry developments to maintain expertise. | S24: 1. Locating relevant data efficiently can be difficult due to the vast amount of information available and potential lack of proper indexing or metadata. 2. Gaining access to necessary data can be hindered by restrictions, lack of interoperability between systems, or inadequate data sharing policies. 3. Integrating data from various sources may be challenging due to differing formats, standards, or terminologies 4. Ensuring data is well-documented, consistently formatted, and contextually rich | T24: Issues: 1. Locating relevant data efficiently can be difficult due to the vast amount of information available and potential lack of proper indexing or metadata. 2. Gaining access to necessary data can be hindered by restrictions, lack of interoperability between systems, or inadequate data sharing policies. 3. Integrating data from various sources may be challenging due to differing formats, standards, or terminologies 4. Ensuring data is well-documented, consistently formatted, and contextually rich. Latent gains: implementing FAIR principles would reduce these challenges and unlock efficiency, compliance, and reuse.
A25: https://github.com/PistoiaAlliance/FAIRMaturityMatrix/blob/FAIR-MM-V1.2/FAIR_personas/Technology_Leader.md | B25: Technology_Leader | C25: Data Enabler | D25: CIO/CTO/CDO-level role shaping enterprise technology and digital strategy with FAIR principles embedded} Senior Information and Digital Technology executive. The most senior executive in an enterprise who works with information technology and computer systems, in order to support enterprise goals. May also drive digital transformations in a company or an organization. For example by converting traditional "analog" businesses to ones relying on digital workflows and infrastructure. The CDO is responsible for whole process of digital transformation. | E25: giovanni.nisato / John Apathy | F25: https://www.wikidata.org/wiki/Q2589465 https://en.wikipedia.org/wiki/Chief_digital_officer | G25: Chief Information Officer (CIO); Chief Digital Officer (CDO); Chief Data Officer (CDO); Chief AI Officer (CAIO) | H25: FAIR_Data_Architect,Business_Analyst,Business_Leader,Business_Owner,Project_Manager,Technology_Leader | I25: Some variation and/or combination of these roles are used at all companies. May be enterprise-wide or divisional (R&D CIO). | J25: { To review with group - V1.2 } | K25: Technology leader. Makes executive decisions regarding matters such as the technology strategies, resourcing strategies, purchase of information and communications technology (ICT) solutions from suppliers, the creation of new ICT systems in-house and the overal capability. Leads and direct the workforce of their specific organization. Recruits managerial talent. Formulates and execute the ICT vision, strategy, governance. Clarifies ICT accountability across functions and roles. Chief Digital Officer may be a more business oriented role that provides expertise in Digital transformation, general management, business analysis, adoption of digital technologies and workflows across functions. Reports to the executive teams and / or the board of directors. Reports to the CEO, or COO or CFO depending on the organisation. | L25: Too many initiatives and not enough budget or resources. Fragmented data landscape, poorly described data that are siloed, of poor quality, and not semantically connected based upon a complex IT systems landscape. Business priorities dictate digital transformation to support data and AI intiatives but majority of budget is consumed by "business as usual" IT needs. | M25: The adoption of FAIR principles delivers strategic and operational value across the data and technology landscape. By improving data quality, accessibility, and interoperability, FAIR makes the organization’s data ecosystem AI-ready and enhances the overall return on technology investments. It enables smoother data integration across platforms, reduces manual effort in data preparation, and minimizes the burden on scientific and technical resources. As a result, technology leaders can focus on accelerating digital transformation, scaling analytics and AI initiatives, and driving innovation through trusted, reusable data assets that support business growth and operational excellence. | N25: must have | O25: Issues: Too many initiatives and not enough budget or resources. Fragmented data landscape, poorly described data that are siloed, of poor quality, and not semantically connected based upon a complex IT systems landscape. Business priorities dictate digital transformation to support data and AI intiatives but majority of budget is consumed by "business as usual" IT needs.. Latent gains: implementing FAIR principles would reduce these challenges and unlock efficiency, compliance, and reuse. | P25: F1 ensures persistent identifiers across the enterprise architecture, providing a foundation for scalable and trusted digital platforms; F2 delivers rich metadata that enables technology leaders to evaluate system interoperability and data readiness; A1 guarantees that enterprise data is reliably accessible via standardized protocols, reducing vendor lock-in and integration costs; I1/I2 enable interoperability and automation across the IT landscape, supporting digital transformation; R1.2 clarifies reuse conditions, allowing safe data sharing with partners and ecosystems; R1.3 promotes alignment with community and industry standards, strengthening the organization’s digital maturity and innovation capacity. | R25: Improve data quality and make data landscape "AI ready" to increase the impact of technology investments on business . Reduce manual effort and subsequent burden on scientific resources for data findability, quality and re-use through data interoperability. {()} {[( F1, A1, I1, R1.1 )]} – F1 provides general benefit for this role; A1 provides general benefit for this role; I1 provides general benefit for this role; R1.1 provides general benefit for this role.
A26: https://github.com/PistoiaAlliance/FAIRMaturityMatrix/edit/FAIR-MM-V1.2/FAIR_personas/Data_Engineer.md | B26: Data_Engineer | C26: Data Enabler | D26: A Data Engineer designs, builds, and manages systems that collect, store, and process large amounts of data. Their job is to ensure that data is accurate, reliable, and accessible for analysis and decision-making. They help organize data so it can easily be discovered, safely accessed by those who need it, used across different systems, and shared or reused by others. In simple terms, Data Engineers make sure data is well-structured and easy to use, while also following best practices so that everyone can get maximum value from data::::::: [RS] --> A Data Engineer builds and maintains the infrastructure needed for data collection, storage, and processing. They design data pipelines, optimize databases, manage large-scale data architectures, and ensure data quality and reliability throughout the analytics process. | E26: Kathleen Rand/ Tara Kumar / Giovanni Nisato | F26: https://www.wikidata.org/wiki/Q104659813 | G26: Research Software Engineer [RS]: Data Infrastructure Engineer; ETL Developer; Data Platform Engineer, Big Data Engineer; Data Pipeline Engineer | H26: FAIR_Data_Architect,Clinical_Data_Manager,Data_Steward,Data_Integration_Specialist,DataOwner,Data_Scientist,Data_Standards_and_Governance_Expert,Ontologist,Researcher | I26: Used at : Amgen | J26: { To review with group - V1.2 } | K26: [RS] The core responsibilities of a Data Engineer is designing and building systems for data collection, storage, and processing, ensuring data is accurate, reliable, and flows efficiently through scalable pipelines. They also prepare and structure data to make it readily available for analysis and informed decision-making. [GN] A Data Engineer in a large pharmaceutical company is responsible for designing, building, and maintaining the infrastructure that enables large-scale data collection, storage, and analysis. Their day-to-day work includes developing ETL (extract-transform-load) pipelines, integrating data from diverse sources such as EDC systems, laboratory information management systems (LIMS), imaging platforms, and real-world evidence datasets. They implement data models, manage cloud or on-premise databases, optimize query performance, and ensure that pipelines are scalable and reliable. Data Engineers also collaborate closely with Data Scientists, Clinical Data Managers, and IT teams to ensure that datasets are structured, clean, and ready for analytics or regulatory submission. | L26: [RS]: Data Engineers face challenges such as handling missing or incomplete data and metadata when aggregating information from heterogeneous sources, especially those that are siloed or lack standardization. They must also deal with differences in data formats, schemas, and source reliability while designing robust and scalable data pipelines. Ensuring secure storage, efficient processing, and compliance with data governance regulations adds layers of complexity to their work. latent gain: Implementing FAIR principles (Findable, Accessible, Interoperable, Reusable) can help address many of these issues, leading to improved efficiency, compliance, and greater potential for data reuse across the organization. Lack of alignment in data formats, poor visbiility on data and metadata completeness, redundancy, lineage, usage [GN] In large pharma, Data Engineers face challenges due to the heterogeneity and complexity of clinical, operational, and research data. Data often resides in siloed systems with inconsistent formats, metadata, and standards. Integrating these diverse sources while preserving data quality, lineage, and security is technically demanding. Maintaining high availability and ensuring compliance with data governance, privacy regulations (e.g., GDPR, HIPAA), and audit requirements adds additional operational complexity. Scaling pipelines to handle growing volumes of genomics, imaging, and real-world evidence data, while keeping them reproducible and maintainable, is another ongoing challenge. | M26: [GN] FAIR principles bring benefits to Data Engineers by providing standardized approaches for data interoperability, discoverability, and reuse. By adopting FAIR-aligned metadata, ontologies, and standardized formats, Data Engineers can streamline data integration and reduce manual mapping efforts. Improved data provenance and accessibility facilitate collaboration across teams and accelerate analytics, machine learning, and regulatory reporting. FAIR practices also support automation of data pipelines, improve reproducibility, and reduce operational risk, enabling Data Engineers to focus more on innovation and optimization rather than time-consuming data wrangling. * Findable (F1–F4): By applying standardized metadata and persistent identifiers, data becomes easier to locate and retrieve across multiple systems. This reduces time spent searching for datasets and ensures that all relevant data can be discovered for analytics or regulatory needs. • Accessible (A1–A2): Implementing well-defined access protocols and ensuring that metadata remains accessible even if the data itself is restricted allows teams to retrieve the data they need efficiently, while maintaining compliance with governance and privacy requirements. • Interoperable (I1–I3): Using controlled vocabularies, ontologies, and standardized data formats enables seamless integration of heterogeneous datasets from EDCs, LIMS, imaging, and real-world evidence systems. This improves cross-team collaboration and reduces errors caused by inconsistent data formats. • Reusable (R1–R1.3): Clear documentation of data provenance, usage licenses, and quality metrics ensures that datasets can be reused for secondary analysis, machine learning, or regulatory reporting. This enhances reproducibility, reduces redundant effort, and supports long-term operational efficiency. | N26: [GN] neds to be clarified - keep / | O26: Issues: Lack of alignment in data formats, poor visbiility on data and metadata completeness, redundancy, lineage, usage [GN] In large pharma, Data Engineers face challenges due to the heterogeneity and complexity of clinical, operational, and research data. Data often resides in siloed systems with inconsistent formats, metadata, and standards. Integrating these diverse sources while preserving data quality, lineage, and security is technically demanding. Maintaining high availability and ensuring compliance with data governance, privacy regulations (e.g., GDPR, HIPAA), and audit requirements adds additional operational complexity. Scaling pipelines to handle growing volumes of genomics, imaging, and real-world evidence data, while keeping them reproducible and maintainable, is another ongoing challenge.. Latent gains: implementing FAIR principles would reduce these challenges and unlock efficiency, compliance, and reuse. | P26: F1 embeds persistent identifiers into pipelines, ensuring that data remains traceable across ingestion and transformation steps; F2 ensures metadata is captured and propagated, enabling automation and monitoring of data flows; A1 guarantees that engineered systems provide secure and reliable access to datasets at scale; I1/I2 enable interoperability between heterogeneous systems and formats, reducing manual reconciliation; R1.1 supports reproducibility of pipeline outputs, ensuring consistent results across environments. | R26: [TKG] F1 embeds globally unique, persistent identifiers into data pipelines, ensuring that data remains traceable across ingestion, transformation, and consumption steps; F2 ensures that rich, standardized metadata is captured and propagated end‑to‑end, enabling automation and monitoring and reliable discovery of data flows; A1 guarantees that engineered systems expose secure and reliable access to datasets at scale via well‑defined, standardized protocols with appropriate authentication and authorization; I1 / I2 enable interoperability between heterogeneous systems and formats by enforcing standard data models, formats, and vocabularies, reducing manual reconciliation and integration effort; R1.1 supports reproducibility of pipeline outputs by capturing and maintaining detailed provenance (input sources, versions, transformation logic, parameters, and runtime environment), ensuring consistent results across environments.
A27: https://github.com/PistoiaAlliance/FAIRMaturityMatrix/edit/FAIR-MM-V1.2/FAIR_personas/Data_Integration_Specialist.md | B27: Data_Integration_Specialist | C27: Data Enabler | D27: A Data Integration Specialist focuses specifically on combining and connecting data from different sources. Their main job is to make sure data from multiple databases and systems works together smoothly, allowing organizations to use all their information more effectively. [RS] --> A Data Integration Specialist focuses on combining data from different sources, ensuring that data from various systems can work together. Their main tasks include designing ETL (Extract, Transform, Load) processes, creating data mappings, and solving integration issues so data flows smoothly between platforms. | E27: Ranu Sharma / Debashree Chakrabarti / Tara kumar | F27: https://www.wikidata.org/wiki/Q1149029 | G27: Data Engineer [GN: this does not seem right] [RS]: Data Integration Engineer | H27: Business_Analyst,Data_Steward,Researcher | I27: Used at AbbVie | J27: { To review with group - V1.2 } | K27: [RS] A Data Integration Specialist locates and connects data from diverse sources, ensuring smooth and accurate integration of data into workflows, pipelines, or models. They focus on making sure that combined data outputs are correct and accessible to downstream users or systems, enabling seamless data flow and interoperability across platforms. | L27: [RS]: Issues: Data Integration Specialists face challenges such as managing missing data and incomplete metadata, especially when working with siloed or isolated data sources. They must reconcile differences in data formats, schemas, and naming conventions to enable smooth integration across platforms. Ensuring secure data exchange and compliance with privacy regulations adds another layer of complexity. Latent gains: Implementation of FAIR principles (Findable, Accessible, Interoperable, Reusable) can help reduce integration difficulties, improve efficiency, support compliance, and enhance data reuse. | M27: ensures FAIR data implementation by developing and maintaining systems that enable seamless data interoperability and integration across different platforms. They ensure data is accessible and compatible by utilizing standardized protocols and formats, promoting efficient data sharing and reuse. {()} {[( F1, A1, I1, R1.1 )]} – F1 provides general benefit for this role; A1 provides general benefit for this role; I1 provides general benefit for this role; R1.1 provides general benefit for this role.Issues: [RS] --> Data Integration Specialists often encounter challenges such as ensuring data quality when merging information from different sources, including handling missing or inconsistent data. They must reconcile varying formats and schemas, making sure diverse systems can communicate effectively. Managing large volumes of data and scaling integration solutions to meet organizational demands is another hurdle. Additionally, they face challenges in maintaining secure data transfers, adhering to privacy regulations, and keeping up with frequent changes in source systems which can disrupt integrations. Monitoring and resolving errors to maintain consistent, reliable data flow is a critical ongoing task. | N27: check if this overlaps with Data Steward? | O27: Issues: Missing data standards or different practices while handling the same type of data make workflow integrations complex.. Latent gains: implementing FAIR principles would reduce these challenges and unlock efficiency, compliance, and reuse. | P27: F1 ensures that data flowing through pipelines is consistently identified with persistent IDs, reducing errors in integration; F2 provides metadata that describes datasets clearly, allowing automated mapping and transformation between systems; A1 guarantees that integrated systems can access source data reliably through standardized protocols; I1 enables semantic interoperability, so data from different domains can be combined without manual reconciliation; I2 supports automated integration processes, reducing maintenance and speeding deployment of new pipelines. | R27: [TKG] F1 ensures that data flowing through pipelines is consistently identified with globally unique, persistent identifiers, reducing errors and ambiguity during integration; F2 provides rich, standardized metadata that describes datasets clearly, allowing automated, machine-driven mapping and transformation between systems; A1 guarantees that integrated systems can access source data reliably and securely through well-defined, standardized protocols; I1 enables semantic interoperability by using shared data models and standard vocabularies, so data from different domains can be combined without manual reconciliation; I2 supports automated, scalable integration processes, reducing maintenance effort and speeding deployment of new or updated pipelines.
A28: https://github.com/PistoiaAlliance/FAIRMaturityMatrix/edit/FAIR-MM-V1.2/FAIR_personas/Data_Quality_Manager.md | B28: Data_Quality_Manager | C28: Data Enabler | D28: {Role defining, monitoring, and remediating data quality issues; FAIR adoption part of remit} Maintains observability, accuracy, completeness, and consistency of enterprise data. | E28: Birgit Meldal | F28: Pfizer | G28: GxP Quality Lead; Regulatory Affairs Specialist; Validation Lead | H28: Business_Owner,Data_Steward,Lab_Manager,Project_Manager | I28: Used at Pfizer | J28: { To review with group - V1.2 } | K28: Provides tooling that can assess data quality during its lifecyle; often in connection with enterprise catalogue or a business application | L28: managing missing data and metadata, esp when sources are siloed | M28: Data maybe FAIR but if it's of low quality it can be useless | O28: Issues: managing missing data and metadata, esp when sources are siloed. Latent gains: implementing FAIR principles would reduce these challenges and unlock efficiency, compliance, and reuse. | P28: F1 provides persistent identifiers that ensure data quality issues can be traced back to specific sources and corrected; F2 enriches metadata so quality dimensions (accuracy, completeness, timeliness) can be assessed and monitored; A1 guarantees that quality-controlled datasets remain accessible to the right users without delays; I1 enables interoperability so quality improvements in one domain flow consistently into others; R1.1 ensures reproducibility of quality checks and audits, demonstrating compliance and improvement over time.
A29: https://github.com/PistoiaAlliance/FAIRMaturityMatrix/edit/FAIR-MM-V1.2/FAIR_personas/FAIR_Data_Architect.md | B29: FAIR_Data_Architect | C29: Data Enabler | D29: A role in an organization focusing on processes, models and policies that manages the generation, use and governance of data, metadata and data standards in a FAIR compliant manner. Develops processes to deliver and maintain FAIR data and services | E29: giovanni.nisato@pistoiaalliance.org/ Nalini Mehta/Baptiste Tauzin | F29: https://pistoiaalliance.github.io/FAIRMaturityMatrix/resources_lexicon | G29: FAIR_Architect; Information_Architect; Data_Architecture Lead; Metadata Modeler | H29: FAIR_Community_Manager,Clinical_Data_Manager,Data_Engineer,Data_Standards_and_Governance_Expert,Ontologist,Technology_Leader | I29: Used at Pfizer, GSK | J29: FAIRMM_V1.1 | K29: A FAIR Architect in a large pharmaceutical organization is responsible for designing and maintaining the enterprise data architecture with a focus on FAIR compliance. This includes defining data models, metadata schemas, ontologies, and standards that ensure all relevant organizational data is findable, accessible, interoperable, and reusable. They develop governance policies, workflows, and pipelines to deliver FAIR data and services, often coordinating with Data Engineers, Clinical Data Managers, and FAIR Community Managers. Their work includes evaluating and implementing data platforms, standardizing data formats, establishing data lineage and provenance frameworks, and ensuring regulatory compliance while enabling cross-functional analytics, AI, and machine learning initiatives. | L29: The Data Architect faces challenges related to heterogeneity, scale, and complexity of pharma data. Data comes from multiple sources (lab equipment, imaging, "omics", electronic note books, clinical trials, real-world evidence) with inconsistent standards, metadata quality, and provenance. Integrating these sources into a coherent (FAIR) framework while balancing regulatory, privacy, and operational requirements is complex. Additionally, driving organization-wide adoption of good (FAIR) data practices requires alignment across multiple stakeholders, overcoming legacy systems, and managing trade-offs between technical feasibility, cost, and usability. | M29: FAIR-aligned data facilitates the work of the data architect in the long run . Standardized metadata, ontologies, and governance frameworks reduce errors, streamline integration, and improve collaboration across departments. Data is consistently structured, discoverable, and of controllable quality across multiple sources, making it easier for teams to access and leverage information for analytics, regulatory submissions, and research. By establishing clear data lineage, provenance, and documentation, FAIR practices enhance transparency and trust in data, support reproducibility, and enable efficient reuse for future projects. Ultimately, FAIR adoption allows the FAIR Architect to optimize data workflows, minimize duplication of effort, and create a scalable, sustainable data infrastructure that drives better decision-making across the organization. | N29: [GN] merged with FAIR architect /done | O29: Issues: The Data Architect faces challenges related to heterogeneity, scale, and complexity of pharma data. Data comes from multiple sources (lab equipment, imaging, "omics", electronic note books, clinical trials, real-world evidence) with inconsistent standards, metadata quality, and provenance. Integrating these sources into a coherent (FAIR) framework while balancing regulatory, privacy, and operational requirements is complex. Additionally, driving organization-wide adoption of good (FAIR) data practices requires alignment across multiple stakeholders, overcoming legacy systems, and managing trade-offs between technical feasibility, cost, and usability.. Latent gains: implementing FAIR principles would reduce these challenges and unlock efficiency, compliance, and reuse. | P29: F1 ensures persistent identifiers are embedded into the data architecture, enabling consistent referencing across systems; F2 enforces rich metadata standards, making datasets machine-actionable and discoverable by design; A1 guarantees accessible services and APIs for data delivery within the enterprise; I1/I2 enable semantic and technical interoperability across platforms and applications; R1.1 ensures reproducibility of workflows and system outputs, providing confidence in architectural reliability.
A30: https://github.com/PistoiaAlliance/FAIRMaturityMatrix/edit/FAIR-MM-V1.2/FAIR_personas/Knowledge-Enabled_Citizen.md | B30: Knowledge-Enabled_Citizen | C30: Data Producer | D30: This role emerges in organizations with high FAIR maturity (levels 4–5) and broad, well-curated data ecosystems, where interoperable, reusable data products are fully embedded into daily operations. Highly educated domain expert empowered by FAIR data products (e.g. query services, knowledge graphs) to find information in complex (FAIR) data sets daily decisions. Organization member who is empowered with access to information, possesses critical thinking skills, enabling them to contribute effectively to the organization’s goals and objectives. | E30: giovanni.nisato@pistoiaalliance.org Kathleen Rand | F30: https://pistoiaalliance.github.io/FAIRMaturityMatrix/resources_lexicon https://www.knowledgescientist.org/ {to double check} | G30: Data Consumer; Intelligence Consumer; Leader; Manager; Business Owner; | H30: Business_Leader,Technology_leader,Business_Analyst,Data_Steward,Researcher | I30: Used at : AstraZeneca, Abbvie | J30: FAIRMM_V1.1 | K30: A Knowledge-Enabled Citizen leverages interoperable data assets and advanced analytical services—such as AI-assisted tools and provenance-linked, machine-interpretable datasets—to explore, validate, and apply information in their domain. These individuals are empowered by transparent access to high-quality data and possess the critical thinking skills needed to translate insights into meaningful contributions toward the organization’s goals. This role typically emerges within organizations operating at FAIR maturity levels 4–5, where data ecosystems are integrated, standardized, and intelligence-driven. | L30: NB: the issues and latent gains are assumed to be largely reduced at high level of FAIR maturity in which this persona emerges. They are reminded for completeness: Issues: data fragmentation across silos and systems; inconsistent metadata and ontologies; limited discoverability of legacy data; unclear or inconsistent regulatory documentation; high duplication of experiments; delayed project timelines due to inefficient data retrieval. Latent gains: clear demonstration of value in standardising processes; opportunities to reduce operational inefficiencies; stronger case for investing in data governance infrastructure; ability to highlight competitive advantage from improved data reusability. | M30: Knowledge-Enabled Citizen can independently access and apply information to drive insight, innovation, and informed decision-making. FAIR benefits include: improved efficiency through fast, reliable access to high-quality, FAIR-aligned data; enhanced regulatory compliance through standardized documentation and transparent provenance; consistent metadata and shared ontologies enabling seamless cross-project and cross-domain data integration; and better utilization of historical, experimental, and real-world data to inform evidence-based decisions. FAIR principles also foster stronger collaboration across research, clinical, and regulatory functions and accelerate innovation through streamlined knowledge discovery and sharing between internal teams and external partners. | N30: to check/ (proposal to merge with Subject Matter/ NB: this would require a significant revision of the FAIR MM text level 5) | O30: NB: the issues and latent gains are assumed to be largely reduced at high level of FAIR maturity in which this persona emerges. They are reminded for completeness: Issues: data fragmentation across silos and systems; inconsistent metadata and ontologies; limited discoverability of legacy data; unclear or inconsistent regulatory documentation; high duplication of experiments; delayed project timelines due to inefficient data retrieval. Latent gains: clear demonstration of value in standardising processes; opportunities to reduce operational inefficiencies; stronger case for investing in data governance infrastructure; ability to highlight competitive advantage from improved data reusability. | P30: F1 ensures that datasets and knowledge objects they use are persistently identified, avoiding ambiguity in scientific or technical references; F2 provides rich metadata that gives necessary context for non-data specialists to assess quality and applicability; A1 guarantees seamless access to the data and knowledge products they rely on, without technical barriers; I1 enables integration of cross-domain knowledge into their specialized research area; R1.3 promotes reuse of trusted community standards, helping them apply external datasets confidently in their own domain.
A31: https://github.com/PistoiaAlliance/FAIRMaturityMatrix/tree/FAIR-MM-V1.2/FAIR_personas | B31: Legal_Data_Expert | C31: Data Enabler | D31: Provides legal and regulatory expertise to ensure data is managed, shared, and reused in compliance with privacy, consent, and intellectual property requirements, while supporting FAIR-aligned practices across the organization.Has expertise in privacy law, data governance, and intellectual property; ability to draft and interpret data sharing agreements; experience in regulatory compliance and ethical data use in research and business contexts. | E31: Giovanni Nisato | F31: {missing URL/URI) | G31: Compliance Officer; Data Protection Specialist; Regulatory Counsel; Risk Management Expert | H31: Business_Leader,Data_Owner,Data_Steward | J31: { To review with group - V1.2 } | K31: Interprets and apply data protection regulations (e.g., GDPR, HIPAA); review and validate licensing frameworks for data reuse; advise on ethical and legal aspects of data sharing; collaborate with Data Stewards and Data Protection Officers to align FAIR practices with legal obligations. | L31: {[Issues: fragmented ownership and opaque provenance; missing persistent identifiers and lineage impede audit trails; inconsistent/insufficient metadata blocks discoverability and lawful-basis checks; unclear or absent licensing/usage terms; ad-hoc access controls and cross-border transfers heighten privacy risk; slow DSAR/eDiscovery due to siloed data; unmanaged retention/disposal; difficulty evidencing compliance in audits; contract negotiations stall over uncertainty. Latent gains if FAIR adopted: clear identifiers and provenance shorten audits/incident response; standard metadata enables lawful-basis and purpose-limitation checks; explicit licenses unlock compliant reuse; role-based access and APIs support consent/least-privilege; automated policy checks reduce legal review time; faster partner onboarding and data sharing; lower regulatory exposure and cost.]} | M31: For a Legal Data Expert, the adoption of FAIR principles strengthens the organization’s ability to manage, share, and reuse data in full compliance with privacy, consent, and intellectual property regulations. By aligning data governance practices with FAIR, legal experts can ensure that data accessibility respects regulatory and contractual access restrictions, safeguarding sensitive information while enabling controlled sharing. At the same time, FAIR enhances the traceability and reproducibility of data handling processes , ensuring that legal and ethical standards are consistently applied and verifiable. This transparency not only supports compliance and audit readiness but also builds organizational trust in data-driven activities, fostering responsible innovation and lawful data reuse across research and business contexts. | N31: must have | O31: Issues: fragmented ownership and opaque provenance; missing persistent identifiers and lineage impede audit trails; inconsistent/insufficient metadata blocks discoverability and lawful-basis checks; unclear or absent licensing/usage terms; ad-hoc access controls and cross-border transfers heighten privacy risk; slow DSAR/eDiscovery due to siloed data; unmanaged retention/disposal; difficulty evidencing compliance in audits; contract negotiations stall over uncertainty. Latent gains if FAIR adopted: clear identifiers and provenance shorten audits/incident response; standard metadata enables lawful-basis and purpose-limitation checks; explicit licenses unlock compliant reuse; role-based access and APIs support consent/least-privilege; automated policy checks reduce legal review time; faster partner onboarding and data sharing; lower regulatory exposure and cost. | P31: A1.2 enforces secure, role-based access aligned with privacy law; R1.1 ensures reproducibility of compliance records for regulators | Q31: Adds value | R31: {[( A1.2, R1.1 )]} – A1.2 ensures access restrictions meet regulatory needs; R1.1 provides reproducibility of legal data handling.
A32: Z | B32: Bioinformatician | D32: Analyze biological data and help ensure it is properly formatted and annotated according to (FAIR) standards. | E32: Ranu Sharma, Nalini Mehta | F32: http://purl.obolibrary.org/obo/NCIT_C165769 https://careers.slas.org/career/bioinformatics-analyst https://www.wikidata.org/wiki/Q2904006 | G32: Bioinformatics Specialist; Data Analyst; Bioinformatics Analyst; Bioinformatics Scientist, Informatician | H32: Business_Analyst,Data_Analyst,Data_Steward,Researcher | I32: Used at AbbVie, GSK, Roche | J32: { To review with group - V1.2 } | K32: Core responsibilities of a Bioinformatician: A bioinformatician specializes in analyzing and interpreting large and complex biological data sets, such as DNA sequences, protein structures, and gene expression patterns. They develop and utilize computational tools and algorithms to make sense of this data and identify patterns and trends that can support the discovery of new drugs and therapies. Bioinformaticians also create visualizations to effectively communicate complex data findings, aiding in the understanding and presentation of results to researchers and stakeholders. They collaborate closely with biologists, medical researchers, and other scientists to design experiments and interpret results, ensuring that computational analyses are integrated effectively with biological research. Through this interdisciplinary approach, bioinformaticians contribute to advancements in personalized medicine and biotechnology, providing valuable insights into complex biological questions. | L32: Challenges: Data Complexity: Handling vast and complex data sets requires accurate management and interpretation, with ongoing concerns about data quality and noise. Technology Advancements: Keeping up with rapidly evolving computational tools, techniques, and biological discoveries necessitates continuous learning and adaptation. Interdisciplinary Communication: Effective collaboration with professionals from biology, medicine, and computer science can be challenging, especially in translating computational findings into biological insights. Resource Limitations: Managing computational resources such as processing power and storage is crucial, particularly when dealing with large-scale data. Ethical Considerations: Navigating ethical and privacy concerns is key when handling sensitive biological data, especially from human subjects. FAIR Standardization Challenges: Achieving consensus on data formats, metadata, and interoperability requires significant effort to harmonize standards across various domains, necessitating ongoing collaboration with multiple stakeholders. Latent Gains: Impact on Healthcare: Contributions to personalized medicine and drug discovery can revolutionize healthcare with targeted therapies and improved patient outcomes. Innovation Potential: Bioinformaticians drive technological and biological advancements through the development of new algorithms and tools. Career Opportunities: High demand for bioinformatics skills opens diverse paths in academia, industry, healthcare, and research institutions. Collaborative Environment: Working in interdisciplinary teams fosters learning and innovation, helping to build broad skill sets and networks. Contribution to Science: Bioinformaticians advance scientific knowledge, uncovering insights that can lead to groundbreaking discoveries in biological processes and diseases. | M32: For a bioinformatician, implementing FAIR principles offers several benefits that enhance their role and contribute to their research effectiveness: Efficient Data Management: By ensuring that data is findable and accessible, bioinformaticians can efficiently retrieve and manage data sets, reducing time spent on data wrangling and allowing for more focus on analysis and interpretation. Facilitated Collaboration: FAIR data practices make it easier to collaborate with colleagues within and across institutions, ensuring smooth data sharing and integration in interdisciplinary projects, which can lead to more comprehensive research findings. Enhanced Data Reusability: With well-documented and reusable data, bioinformaticians can apply existing datasets to new research questions, maximizing the utility of data and encouraging innovation without duplicating effort. Improved Research Transparency and Reproducibility: FAIR principles enhance the transparency and reproducibility of research by providing clear and accessible data provenance and documentation, strengthening the reliability and credibility of findings. Access to Wider Research Networks: Implementing FAIR principles can connect bioinformaticians to a broader network of data and researchers, increasing opportunities for collaboration, resource sharing, and exposure to diverse insights and methodologies. These benefits help bioinformaticians navigate and maximize the potential of data within their role, driving more effective research outcomes and contributing to advances in the field. {()} {[( F2, I1, R1.2 )]} – F2 supports discovery of datasets via metadata for analysis; I1 ensures bioinformatics data can integrate with other sources; R1.2 clarifies reuse conditions for derived results. | N32: [GN]. very specific / wait and confirm interest before implementation | O32: Issues: Challenges: Data Complexity: Handling vast and complex data sets requires accurate management and interpretation, with ongoing concerns about data quality and noise. Technology Advancements: Keeping up with rapidly evolving computational tools, techniques, and biological discoveries necessitates continuous learning and adaptation. Interdisciplinary Communication: Effective collaboration with professionals from biology, medicine, and computer science can be challenging, especially in translating computational findings into biological insights. Resource Limitations: Managing computational resources such as processing power and storage is crucial, particularly when dealing with large-scale data. Ethical Considerations: Navigating ethical and privacy concerns is key when handling sensitive biological data, especially from human subjects. FAIR Standardization Challenges: Achieving consensus on data formats, metadata, and interoperability requires significant effort to harmonize standards across various domains, necessitating ongoing collaboration with multiple stakeholders. Latent Gains: Impact on Healthcare: Contributions to personalized medicine and drug discovery can revolutionize healthcare with targeted therapies and improved patient outcomes. Innovation Potential: Bioinformaticians drive technological and biological advancements through the development of new algorithms and tools. Career Opportunities: High demand for bioinformatics skills opens diverse paths in academia, industry, healthcare, and research institutions. Collaborative Environment: Working in interdisciplinary teams fosters learning and innovation, helping to build broad skill sets and networks. Contribution to Science: Bioinformaticians advance scientific knowledge, uncovering insights that can lead to groundbreaking discoveries in biological processes and diseases.. Latent gains: implementing FAIR principles would reduce these challenges and unlock efficiency, compliance, and reuse. | P32: F2 provides metadata that improves discovery of relevant bio datasets; I1 ensures bioinformatics data can integrate with other sources; R1.2 clarifies reuse conditions for derived bioinformatic results
A33: z | B33: Deprecated-Advanced_Data_Analysis_and_Insights_Professional | D33: {Business-facing analyst translating data into strategic insights} Applies advanced analytics to patient and healthcare data to uncover trends and support integrated deliverables. | E33: khrl@novonordisk.com | F33: {missing URL/URI) | G33: Senior Data Analyst; Real World Evidence Specialist | H33: Business_Analyst,Data_Scientist,Data_Steward,Researcher | I33: Used at Novo Nordisk | J33: { To review with group - V1.2 } | K33: Identifies patterns in patient data, collaborates across functions, ensures analytical rigor. | L33: Complexity in data harmonization and cross-functional alignment. Gains: deeper insights, robust evidence. | M33: FAIR data principles provide a foundation for scalable analytics and improved data traceability across complex systems. Persistent identifiers ensure metrics remain consistent, while rich metadata enables rapid assessment of data quality and relevance. Reliable access to trusted datasets supports timely insights, and seamless data integration across domains allows for holistic, cross-functional analysis. Moreover, reproducibility strengthens auditability and regulatory readiness, enhancing confidence in analytical outcomes and supporting compliant, insight-driven decision-making. | N33: [GN] label is too long- merge with Data_Analysis_and_Insights_Manager | O33: Issues: Complexity in data harmonization and cross-functional alignment. Gains: deeper insights, robust evidence.. Latent gains: implementing FAIR principles would reduce these challenges and unlock efficiency, compliance, and reuse. | P33: F1 ensures datasets have persistent identifiers so business metrics are traceable across systems; F2 provides rich metadata that allows analysts to evaluate data quality and relevance before use; A1 guarantees stable access to trusted datasets needed for timely insights; I1 enables integration of data from multiple business domains for holistic analysis; R1.1 ensures that reported insights are reproducible, supporting auditability and stakeholder confidence.
A34: z | B34: Deprecated-Data_Analysis_and_Insights_Manager | D34: {Manager aligning analytics activities to business priorities and stakeholder needs} Supports stakeholders with real-world data analytics, particularly in healthcare and clinical settings, to inform decisions and generate evidence. | E34: khrl@novonordisk.com AD | F34: {missing URL/URI) | G34: Real World Data Analyst; Health Data Manager | H34: Advanced_Data_Analysis_and_Insights_Professional,Business_Owner,Lab_Manager,Project_Manager | I34: Used at Novo Nordisk | J34: { To review with group - V1.2 } | K34: Analyzes medical claims, health records, and real-world evidence to support decisions. | L34: Data privacy, integration of diverse data types. Gains: better patient insights, faster evidence generation. | M34: Enhances data linkage, ensures compliance, supports secondary use of data. | N34: [GN] consolidate with Advanced_Data_Analysis_and_Insights_Professional | O34: Issues: Data privacy, integration of diverse data types. Gains: better patient insights, faster evidence generation.. Latent gains: implementing FAIR principles would reduce these challenges and unlock efficiency, compliance, and reuse. | P34: F1 ensures that the datasets used for team analyses are consistently identified, supporting alignment across projects; F2 provides rich metadata that helps managers assess data quality and relevance before assigning tasks; A1 guarantees that their teams have reliable access to the right data resources, reducing delays; I1 allows integration of datasets across domains, enabling holistic insights that meet business requirements; R1.1 assures reproducibility of reported analyses, strengthening trust in outputs delivered to stakeholders.
A35: z (duplicate line) | B35: Deprecated-Master_Data_Manager | D35: Role ensuring authoritative single sources of truth across the enterprise (e.g., products, customers, materials). Manages the master data in a given business domain | E35: Birgit/ Avinash | F35: {missing URL/URI) | G35: Enterprise Data Manager; Data Domain Manager; Master Data Lead; Master Data Steward; Master Data Coordinator; Reference Data Manager; | H35: Business_Owner,Data_Owner,Curator,Lab_Manager,Project_Manager | I35: used at Pfizer | J35: { To review with group - V1.2 } | K35: Define and maintain enterprise master data standards; oversee creation, quality, and governance of master data domains (e.g., products, customers, materials); ensure harmonization and alignment across business units and IT systems; resolve data ownership conflicts and redundancies; collaborate with Data Stewards, Architects, and Analysts to embed FAIR principles into master data processes; monitor data quality KPIs and enforce remediation workflows; support regulatory reporting and compliance through accurate, consistent master data. | L35: Issues: duplicated and inconsistent master data across business units; lack of persistent identifiers creates ambiguity in reporting; poor metadata prevents discovery of authoritative records; siloed systems hinder integration and interoperability; unclear ownership slows resolution of data quality issues; regulatory submissions are delayed or error-prone due to conflicting datasets. Latent gains if FAIR adopted: F1 enables persistent identifiers that define single sources of truth; F2-rich metadata supports discoverability and governance; A1 provides secure yet consistent access across systems; I1/I2 ensure interoperability between domains and applications; R1.1/R1.2 guarantee reproducible, licensed reuse of master data, reducing compliance risk and speeding reporting.]} | M35: (missing) | N35: [GN] combined with Reference_Data_Manager / --- > Master_data_Manager | O35: data from different sources can use different terminologies but is actually the same type of data. {[Issues: duplicated and inconsistent master data across business units; lack of persistent identifiers creates ambiguity in reporting; poor metadata prevents discovery of authoritative records; siloed systems hinder integration and interoperability; unclear ownership slows resolution of data quality issues; regulatory submissions are delayed or error-prone due to conflicting datasets. Latent gains if FAIR adopted: F1 enables persistent identifiers that define single sources of truth; F2-rich metadata supports discoverability and governance; A1 provides secure yet consistent access across systems; I1/I2 ensure interoperability between domains and applications; R1.1/R1.2 guarantee reproducible, licensed reuse of master data, reducing compliance risk and speeding reporting.]} | P35: F1 ensures authoritative entities (e.g., products, customers) have persistent identifiers, preventing duplication and ambiguity across systems; F2 provides rich metadata that defines business meaning, lineage, and ownership of master data; A1 guarantees secure but consistent access to authoritative master data across business units; I1/I2 enable interoperability and automated synchronization between enterprise systems; R1.1 assures reproducibility of reports and compliance filings that depend on master data; R1.2 clarifies reuse conditions, allowing trusted sharing of master data across internal and external stakeholders. | R35: data from multiple sources can be combined in metanalyses; data becomes FAIR

Sheet Types of personas
B2: Data Producer
B3: Data Consumer
B4: Data Enabler

Sheet DRAFT2025_Table_personas_FAIR
A1: Terms describing "roles" or"personas" in FAIR data principle implementation. These are all "stakeholders" in FAIR data principles implementation. The purpose of this document is to collect data that will be sued to update the FAIR maturity matrix framework as well as the FAIR business framework.
B2: name or email | C2: ORCID | E2: name or email | F2: ORCID
B3: giovanni.nisato@pistoiaalliance.org | C3: https://orcid.org/0000-0002-5824-0061 | E3: Katharina Lang (⁠KHRL) | F3: {enter your ORCID - takes 2 min to create one}
B4: Nalini Mehta | C4: {enter your ORCID - takes 2 min to create one} | E4: Kathleen Rand | F4: {enter your ORCID - takes 2 min to create one}
B5: ⁠Sharma, Ranu | C5: https://orcid.org/0009-0004-6207-0773 | E5: Karien Pype | F5: {enter your ORCID - takes 2 min to create one}
B6: Meldal, Birgit | C6: {enter your ORCID - takes 2 min to create one} | E6: Nalini Mehta | F6: {enter your ORCID - takes 2 min to create one}
B7: Chris Day | E7: Debashree Chakrabarti | F7: {enter your ORCID - takes 2 min to create one}
B8: John Apathy | C8: {enter your ORCID - takes 2 min to create one} | E8: Emiliano Reynares | F8: {enter your ORCID - takes 2 min to create one}
B9: Baptiste Tauzin | E9: Avinash Dixit | F9: https://orcid.org/0009-0005-8204-6655
B10: Ted Slater | E10: Philippe Rocca-Serra
B11: Nick Lynch | C11: https://orcid.org/0000-0002-8997-5298
D12: for additions by experts | E12: for additions by experts | G12: for additions by experts
A13: Label | B13: description_of_role | C13: Content_Added_by | D13: Source URL/URI | E13: Synonyms | F13: Related persona | G13: Notes on usage | H13: FAIRMM version | I13: Persona_tasks | J13: Issues_latent_gains | K13: Potential_FAIR_benefits | L13: Must have/ nice to have / park for the moment
A14: short name of the role, text. Must-have for FAIR Maturity Matrix documentation. | B14: Definition of the role, text. Ideally, this is the same as a known, existing definition we can refer to publicly. Must-have for FAIR Maturity Matrix documentation. | C14: identification of the person that added content in a given line in this document. For internal use, not for ppublic disclosure. | D14: URL/ URI of the text of the definition. Nice to have for FAIR Maturity Matrix documentation. | E14: Known synonyms of this role. Nice to have for FAIR Maturity Matrix documentation. | F14: List of related roles - no hierarchy. Nice to have for FAIR Maturity Matrix documentation and for the FAIR Business Value frame. | G14: Usage in different organisations; non exahustive, just some examples. Nice to have. | H14: Version of the FAIR Maturity Matrix in which this role appears, or recommendation to add to a new version. Based on FAIR expert inputs (organize session for this) | I14: What are the typical tasks, activities or "jobs" of the persona. | J14: Description of the challenges a given persona has with data. | K14: What benefits can FAIR data bring to the persona. | L14: Is the persona necessary in the FAIR MM ? Is it a duplicate? Can it be merged with another persona?
A15: Label_persona | B15: description_of_role | C15: Content_Added_by | D15: Source URL/URI | E15: Synonyms | F15: Related persona | G15: Notes on usage, relation to other roles or personas | H15: FAIRMM version | I15: Persona_tasks | J15: Issues_latent_gains | K15: Potential_FAIR_benefits | L15: Must have/ nice to have / park for the moment
A16: (Bio)informatician (Do we explicitly need to mention the bio part or generalise to Informatician) | B16: Analyze biological data and help ensure it is properly formatted and annotated according to FAIR standards. | C16: Ranu Sharma, Nalini Mehta | D16: http://purl.obolibrary.org/obo/NCIT_C165769 https://careers.slas.org/career/bioinformatics-analyst | E16: Bioinformatian, Bioinformatics Specialist, Data Analyst, Bioinformatics analyst, Bioinformatics Scientist, Informatician and flavours of informatician | F16: Data Analyst | G16: Used at AbbVie, GSK, Roche | H16: { To review with group - V1.2 } | I16: Core responsibilities of a Bioinformatician: A bioinformatician specializes in analyzing and interpreting large and complex biological data sets, such as DNA sequences, protein structures, and gene expression patterns. They develop and utilize computational tools and algorithms to make sense of this data and identify patterns and trends that can support the discovery of new drugs and therapies. Bioinformaticians also create visualizations to effectively communicate complex data findings, aiding in the understanding and presentation of results to researchers and stakeholders. They collaborate closely with biologists, medical researchers, and other scientists to design experiments and interpret results, ensuring that computational analyses are integrated effectively with biological research. Through this interdisciplinary approach, bioinformaticians contribute to advancements in personalized medicine and biotechnology, providing valuable insights into complex biological questions. | J16: Challenges: Data Complexity: Handling vast and complex data sets requires accurate management and interpretation, with ongoing concerns about data quality and noise. Technology Advancements: Keeping up with rapidly evolving computational tools, techniques, and biological discoveries necessitates continuous learning and adaptation. Interdisciplinary Communication: Effective collaboration with professionals from biology, medicine, and computer science can be challenging, especially in translating computational findings into biological insights. Resource Limitations: Managing computational resources such as processing power and storage is crucial, particularly when dealing with large-scale data. Ethical Considerations: Navigating ethical and privacy concerns is key when handling sensitive biological data, especially from human subjects. FAIR Standardization Challenges: Achieving consensus on data formats, metadata, and interoperability requires significant effort to harmonize standards across various domains, necessitating ongoing collaboration with multiple stakeholders. Latent Gains: Impact on Healthcare: Contributions to personalized medicine and drug discovery can revolutionize healthcare with targeted therapies and improved patient outcomes. Innovation Potential: Bioinformaticians drive technological and biological advancements through the development of new algorithms and tools. Career Opportunities: High demand for bioinformatics skills opens diverse paths in academia, industry, healthcare, and research institutions. Collaborative Environment: Working in interdisciplinary teams fosters learning and innovation, helping to build broad skill sets and networks. Contribution to Science: Bioinformaticians advance scientific knowledge, uncovering insights that can lead to groundbreaking discoveries in biological processes and diseases. | K16: For a bioinformatician, implementing FAIR principles offers several benefits that enhance their role and contribute to their research effectiveness: Efficient Data Management: By ensuring that data is findable and accessible, bioinformaticians can efficiently retrieve and manage data sets, reducing time spent on data wrangling and allowing for more focus on analysis and interpretation. Facilitated Collaboration: FAIR data practices make it easier to collaborate with colleagues within and across institutions, ensuring smooth data sharing and integration in interdisciplinary projects, which can lead to more comprehensive research findings. Enhanced Data Reusability: With well-documented and reusable data, bioinformaticians can apply existing datasets to new research questions, maximizing the utility of data and encouraging innovation without duplicating effort. Improved Research Transparency and Reproducibility: FAIR principles enhance the transparency and reproducibility of research by providing clear and accessible data provenance and documentation, strengthening the reliability and credibility of findings. Access to Wider Research Networks: Implementing FAIR principles can connect bioinformaticians to a broader network of data and researchers, increasing opportunities for collaboration, resource sharing, and exposure to diverse insights and methodologies. These benefits help bioinformaticians navigate and maximize the potential of data within their role, driving more effective research outcomes and contributing to advances in the field.
A17: (FAIR) Data Architect (proposal : keep / combine with FAIR architect) | B17: A role in an organization focusing on processes, models and frameworks/policies that manages the generation, use and governance of data, metadata and data standards in the most optimal form/a FAIR compliant manner. Develops processes to deliver and maintain FAIR data and services | C17: giovanni.nisato@pistoiaalliance.org/ Nalini Mehta/Baptiste Tauzin | D17: https://pistoiaalliance.github.io/FAIRMaturityMatrix/resources_lexicon | E17: FAIR architect | F17: Data Engineers, Clinical Data Managers, (FAIR) Community Manager, C-level tech leaders | G17: Used at Pfizer, GSK | H17: FAIRMM_V1.1 | I17: [GN] A FAIR Architect in a large pharmaceutical organization is responsible for designing and maintaining the enterprise data architecture with a focus on FAIR compliance. This includes defining data models, metadata schemas, ontologies, and standards that ensure all organizational data is findable, accessible, interoperable, and reusable. They develop governance policies, workflows, and pipelines to deliver FAIR data and services, often coordinating with Data Engineers, Clinical Data Managers, and FAIR Community Managers. Their work includes evaluating and implementing data platforms, standardizing data formats, establishing data lineage and provenance frameworks, and ensuring regulatory compliance while enabling cross-functional analytics, AI, and machine learning initiatives. | J17: [GN] The Data Architect faces challenges related to heterogeneity, scale, and complexity of pharma data. Data comes from multiple sources (lab equipment, imaging, "omics", electronic note books, clinical trials, real-world evidence) with inconsistent standards, metadata quality, and provenance. Integrating these sources into a coherent (FAIR) framework while balancing regulatory, privacy, and operational requirements is complex. Additionally, driving organization-wide adoption of good (FAIR) data practices requires alignment across multiple stakeholders, overcoming legacy systems, and managing trade-offs between technical feasibility, cost, and usability. | K17: [GN] , FAIR-aligned data facilitates the work of the data architect in the long run . Standardized metadata, ontologies, and governance frameworks reduce errors, streamline integration, and improve collaboration across departments.. Data is consistently structured, discoverable, and of controllable quality across multiple sources, making it easier for teams to access and leverage information for analytics, regulatory submissions, and research. By establishing clear data lineage, provenance, and documentation, FAIR practices enhance transparency and trust in data, support reproducibility, and enable efficient reuse for future projects. Ultimately, FAIR adoption allows the FAIR Architect to optimize data workflows, minimize duplication of effort, and create a scalable, sustainable data infrastructure that drives better decision-making across the organization. • Findable (F1–F4): Consistent metadata and identifiers make datasets easy to locate and track across the enterprise. • Accessible (A1–A2): Defined access protocols and persistence policies ensure authorized users can reliably retrieve datasets and metadata. • Interoperable (I1–I3): Standardized ontologies, controlled vocabularies, and formats enable seamless integration of heterogeneous datasets across departments and systems. • Reusable (R1–R1.3): Clear provenance, licensing, and quality standards allow data to be reused for regulatory submissions, secondary research, and AI/ML applications, reducing duplication and enhancing data value. | L17: keep / combine with FAIR architect
A18: (FAIR) Trainer | B18: Trainers design and deliver training programs to a variety of stakeholders ranging from researchers to business leaders and project teams across organisation functions (R&ED, but also development, clinical, franchises), with a focus on awareness and best practice implementation of FAIR data principles. The role supports compliance with corporate data governance policies, regulatory expectations, and scientific needs. It interfaces and interacts woth | C18: giovanni nisato | D18: adapted from: https://rdmkit.elixir-europe.org/trainer | F18: Researcher, Data Analyst, Citized Data Scientists, Know | I18: Collaborate with data governance leads, technology leads, data architects, community managers and researcher teams to identify training needs aligned with corporate strategy; design tailored, role-specific training schedules; create high-quality, compliant, and FAIR-aligned learning materials (presentations, manuals, e-learning modules, job aids); deliver in-person, virtual, and hybrid sessions combining policy awareness with hands-on skills; promote company-approved and community recommended tools, standards, and workflows; adapt delivery for varied therapeutic areas, modalities, and stages of development (R&D, etc); establish continuous improvement processes through structured feedback and impact measurement. Keep track of FAIR training offering outside of the organisation. | J18: The lower the organisation FAIR maturity level, the higher the complexity of the role and the need to create awareness. Lack of clarity and alignment in terms of needs and requirements from the organisations can be expected. At more advanced maturity levels, traning may become diversified and tuned to the needs of differen stakeholders, from business leaders, to researchers, to Data Stewards and Architects. In a change management process, the value of the training, FAIR and data-centric approach may be challenged. | K18: Benefit from success stories to articulate the "why" of the training. Ability to re-use FAIR training materials. Ability to use open standards, showcase examples from FAIR implementation journeys and FAIR implementation profiles. Benefit from clearer metrics and frameworks to assess FAIR data sets (FAIR indicators) and organisations. (FAIR MM). Higher impact of training due to availability of FAIR compliant data and examples of implementation.
A19: (FAIR) Trainer | B19: Trainers design and deliver training programs to a variety of stakeholders ranging from researchers to business leaders and project teams across organisation functions (R&ED, but also development, clinical, franchises), with a focus on awareness and best practice implementation of FAIR data principles. The role supports compliance with corporate data governance policies, regulatory expectations, and scientific needs. It interfaces and interacts woth | C19: giovanni nisato | D19: adapted from: https://rdmkit.elixir-europe.org/trainer | F19: Researcher, Data Analyst, Citized Data Scientists, Know | I19: Collaborate with data governance leads, technology leads, data architects, community managers and researcher teams to identify training needs aligned with corporate strategy; design tailored, role-specific training schedules; create high-quality, compliant, and FAIR-aligned learning materials (presentations, manuals, e-learning modules, job aids); deliver in-person, virtual, and hybrid sessions combining policy awareness with hands-on skills; promote company-approved and community recommended tools, standards, and workflows; adapt delivery for varied therapeutic areas, modalities, and stages of development (R&D, etc); establish continuous improvement processes through structured feedback and impact measurement. Keep track of FAIR training offering outside of the organisation. | J19: The lower the organisation FAIR maturity level, the higher the complexity of the role and the need to create awareness. Lack of clarity and alignment in terms of needs and requirements from the organisations can be expected. At more advanced maturity levels, traning may become diversified and tuned to the needs of differen stakeholders, from business leaders, to researchers, to Data Stewards and Architects. In a change management process, the value of the training, FAIR and data-centric approach may be challenged. | K19: Benefit from success stories to articulate the "why" of the training. Ability to re-use FAIR training materials. Ability to use open standards, showcase examples from FAIR implementation journeys and FAIR implementation profiles. Benefit from clearer metrics and frameworks to assess FAIR data sets (FAIR indicators) and organisations. (FAIR MM). Higher impact of training due to availability of FAIR compliant data and examples of implementation.
A20: {FAIR} Community Manager (proposal/ keep merge with "Community of Practice Organiser") | B20: An individual or group responsible for facilitating and managing a community of practice (CoP). The organizer’s role involves coordinating meetings, events, and activities for the community, creating channels for communication and knowledge sharing, and fostering a supportive and inclusive environment where members feel comfortable exchanging ideas and experiences. They may also be involved in recruiting new members, setting goals and objectives for the community, and ensuring that it remains vibrant and relevant to its members’ needs and interests. Person who organizes groups of people around shared aims - see https://the-turing-way.netlify.app/collaboration/research-infrastructure-roles/community-manager.html | C20: giovanni.nisato@pistoiaalliance.org | D20: https://the-turing-way.netlify.app/collaboration/research-infrastructure-roles/community-manager.html https://pistoiaalliance.github.io/FAIRMaturityMatrix/resources_lexicon | E20: Community of Practice Organiser | F20: data stewards, clinical data managers, researchers, subject matter experts | G20: {nice to have/ to complete} | H20: FAIRMM_V1.1 | I20: [GN] A (FAIR) Community Manager in pharma is responsible for building and nurturing a community of practice (CoP) around FAIR data principles, standards, and best practices. Their activities include organizing workshops, webinars, and discussion forums; coordinating cross-functional meetings with data stewards, clinical data managers, scientists, and IT teams; and maintaining communication channels such as mailing lists, Slack/Teams channels, or internal portals. They curate and disseminate knowledge, including FAIR guidelines, metadata standards, and interoperability frameworks. Additionally, they track emerging trends in data management and FAIR adoption, and actively recruit new members to ensure the community reflects diverse roles and perspectives within the organization. | J20: [GN] The FAIR Community Manager faces challenges in aligning stakeholders from different departments and skill levels around common FAIR objectives. Large pharma environments often have siloed data systems, heterogeneous standards, and varying levels of FAIR awareness, making it difficult to foster meaningful engagement and knowledge sharing. Capturing and disseminating lessons learned, best practices, and metadata standards in a way that is accessible, actionable, and trusted by the community can also be complex. Moreover, demonstrating the tangible value of FAIR adoption to senior management and ensuring consistent participation across global teams requires both diplomacy and strategic planning. | K20: [GN] the 15 F AIR data principles as well as other public artefacts provide the FAIR Community Manager with a shared framework and language for engagement across the organization. By sharing "success stories" of FAIR data practices, they can demonstrate value for community members, such as easier access to datasets, reduced duplication of effort, and improved cross-study analytics. FAIR-aligned processes enable more consistent documentation, metadata capture, and provenance tracking, which the community can showcase as concrete successes. Ultimately, FAIR data empowers the manager to strengthen collaboration, accelerate learning, and drive a culture of continuous improvement and innovation in data management practices across the company. • Findable (F1–F4): FAIR principles give the community a shared language and standards for cataloguing and indexing datasets, making it easier to discover relevant information and resources for members across departments. • Accessible (A1–A2): FAIR-aligned systems and clear access protocols ensure that knowledge and datasets can be shared across teams, regions, and functions while respecting data governance and security policies. • Interoperable (I1–I3): Using standardized metadata, controlled vocabularies, and ontologies facilitates collaboration across diverse teams and tools. This enables members to combine datasets and insights effectively, even when sourced from different platforms or departments. • Reusable (R1–R1.3): By promoting consistent documentation, provenance tracking, and clear usage licenses, the community ensures that datasets and shared best practices can be reliably reused for analytics, regulatory work, training, and innovation initiatives. This strengthens engagement and demonstrates tangible value to the organization. | L20: Keep in FAIR MM version > 1
A21: Advanced Data Analysis & Insights Professional | B21: Applies advanced analytics to patient and healthcare data to uncover trends and support integrated deliverables. | C21: khrl@novonordisk.com | D21: {missing URL/URI) | E21: Senior Data Analyst, Real World Evidence Specialist | F21: Data Scientist | G21: Used at Novo Nordisk | H21: { To review with group - V1.2 } | I21: Identifies patterns in patient data, collaborates across functions, ensures analytical rigor. | J21: Complexity in data harmonization and cross-functional alignment. Gains: deeper insights, robust evidence. | K21: Scalable analytics, improved data traceability, supports regulatory submissions.
A22: Business Analyst | B22: A role in organisation in implementing FAIR principles by acting as the bridge between scientific, technical, and business stakeholders. They identify gaps in data accessibility and interoperability, gather requirements, and help define a roadmap for FAIR adoption. | C22: Avinash Dixit, Debashree Chakrabarti | D22: DAMA-DMBOK2: Roles & Responsibilities | E22: Data Modeller, Business System Consultant (BSC), Business Relationship Manager (BRM) Data Analyst | F22: IT system owner (ITSO), Business Owner | G22: Used at : AstraZeneca, Abbvie | H22: { To review with group - V1.2 } | I22: Responsible for tech stack upkeep for a team/lab/therapeutic area. E.g. Architecture and Data workflow, Inventory of software/hardware/infrastructure applications, purchasing and maintenance, identifying gaps / end of life processes and updating with new technology | J22: Legacy platforms incompatible with new technology. Scientists / users of technology fail to prioritize upkeep. | K22: Avoid redundancy, vendor locking and management of systems proactively. Manage petabytes of data efficiently using ontologies and archive policies.
A23: Business Leader - Chief Executive Officer (CEO), Chief Operating Officer, Chief Financial Officer (CFO), Functional Line Leader - Head of R&D, Head of Manufacturing, Supply Chain, CMC, etc. | B23: In an organization, personnel holding roles such as CEO, CFO, CTO, COO, or Functional Line Leaders with executive and strategy level decision- making capacities. | C23: giovanni.nisato / Karien Pype | D23: https://www.wikidata.org/wiki/Q484876 | E23: CEO, COO, CFO, President, etc. | F23: CIO, COO, CDO, Business Analysts | G23: Used at: all companies | H23: { To review with group - V1.2 } | I23: Making data-driven strategic decisions, performance and KPI management, engaging with investors and stakeholders with reliable data, enabling digital and data transformation, managing risk and compliance, supporting M&A, licensing, and due diligence | J23: Data fragmentation, data in silos, poor data re-usability, lack in visibility into data (which data do we have? Can we trust it?), barriers for scaling AI/ML initiatives, compliance and data governance risks | K23: Strategic benefits: faster time to market of therapies/drugs thanks to iImproved data discoverability, reusability accelerate research cycles, and easier identification of drug targets, biomarkers, and clinical trial insights.
A24: Business Owner | B24: designated individual responsible for the business value, requirements, and success of a process, product, system, or dataset. | C24: Kathleen Rand , Chris Day | D24: DAMA-DMBOK2: Appendix A: Roles & Responsibilities Matrix | E24: Business Data Owner (BDO) Data Asset Owner Business Executive & Manager | F24: Data Owner Product Owner Metadata Specialist Business Process Lead Data Warehouse Architect Data Management Professionals Other IT Professionals Information Architects Subject Matter Experts Data Stewardship Council | G24: Used at : Amgen Used within DAMA DMBoKV2 | H24: { To review with group - V1.2 } | I24: Responsible for understanding the FAIR needs. | J24: 1. Unclear Business Ownership of Data Assets FAIR View: Without clear ownership, stewardship for making data Findable, Accessible, Interoperable, and Reusable is often neglected. DAMA View: Data Ownership (within Data Governance) must be clearly defined, yet business owners are often unaware or unclear about their responsibilities. Impact: Data is treated as a by-product, not an asset, hindering strategic data enablement. 2. Lack of Alignment Between Business Goals and Data Strategy FAIR View: FAIRification efforts may be driven by IT or compliance teams, not aligned with value streams or KPIs that matter to business owners. DAMA View: Poor alignment across Data Strategy, Business Process Management, and Data Governance. Impact: Investments in FAIR may appear technical or academic, with unclear ROI for the business owner. 3. Data is Not Trusted or Understood FAIR View: If metadata and provenance are absent or poor, trust is undermined. DAMA View: Data Quality and Metadata Management are foundational, yet often fragmented. Impact: Business owners cannot rely on data for critical decision-making, reducing willingness to sponsor data initiatives. 4. Inconsistent Data Accessibility Across Functions FAIR View: Access policies are inconsistent, siloed, or not machine-actionable. DAMA View: Access & Security Management is often reactive, not driven by business use cases. Impact: Business owners encounter roadblocks or delays when accessing the data they are accountable for, impacting operational agility. 5. Data Silos Obstruct Reuse and Interoperability FAIR View: Poor interoperability blocks data integration and reuse across functions or systems. DAMA View: Reference and Master Data Management is often insufficient, leading to duplication and reconciliation overhead. Impact: Business owners can't extract cross-domain insights or scale analytics and AI initiatives. 6. Lack of Skills and Capacity to Interpret FAIR Metrics FAIR View: Maturity assessments and metrics may seem abstract or disconnected from business outcomes. DAMA View: Literacy gaps in both data management and data value communication. Impact: Business owners struggle to justify ongoing FAIR investment or demonstrate value to executive stakeholders. 7. Regulatory and Compliance Burden without Strategic Leverage FAIR View: Compliance is often a reactive cost centre rather than an opportunity to enhance FAIR maturity. DAMA View: Regulatory alignment is part of Governance and Risk Management but is rarely used as a FAIR catalyst. Impact: FAIR seen as a cost rather than a business enabler, unless reframed. 8. No Clear Business Value Framework for FAIR Data FAIR View: FAIR Maturity Models exist, but are not always coupled to business value frameworks like VMM or ROI calculations. DAMA View: Business Value Realisation is often implicit and not operationalised within Data Governance. Impact: Business owners cannot link FAIR efforts to quantifiable business drivers (e.g. revenue, speed to market, cost reduction). | K24: A Business Owner can derive tangible and strategic benefits from FAIR data principles when aligned with business goals. These benefits span operational efficiency, regulatory compliance, innovation enablement, and risk reduction. Below is a breakdown of the core business benefits a Business Owner could realise from the adoption of FAIR principles, framed in alignment with DAMA-DMBOK functions. 1. Improved Decision-Making and Time-to-Insight FAIR Value: Findable and Accessible data enables faster retrieval and reduces effort spent on locating, reconciling, or verifying data. Business Impact: Quicker evidence-based decisions; faster time-to-market; improved responsiveness to customers and regulators. 🧠 “Less time finding data, more time using it.” 2. Higher Trust and Data Quality FAIR Value: Provenance and metadata increase trust in data authenticity and lineage. Business Impact: Reduces operational errors and misinformed decisions; supports data-dependent processes like forecasting, modelling, and reporting. 📉 Reduction in data rework, reconciliation, and audit failures. 3. Cross-Functional Interoperability and Collaboration FAIR Value: Interoperable data supports reuse across domains, tools, and teams. Business Impact: Enables integrated reporting, joined-up customer views, and cross-functional analytics. Supports M&A and organisational restructuring with minimal friction. 4. Regulatory Compliance and Reduced Risk FAIR Value: Reusable data with clear usage rights and provenance eases compliance with data regulations (e.g. GDPR, ISO 20022, FDA). Business Impact: Reduces risk of fines, audit failures, and non-compliance. Enables proactive reporting and transparency. 5. Increased Data Reusability = Lower Cost of Data FAIR Value: Standard formats, metadata, and semantic clarity reduce data duplication and enhance reuse. Business Impact: Cuts down on procurement of redundant data, manual reconciliation, and bespoke pipelines. 6. Enablement of AI, Automation, and Innovation FAIR Value: Machine-actionable metadata and standard ontologies support automated discovery and intelligent processing. Business Impact: Accelerates AI/ML initiatives, digital twins, semantic search, and knowledge graph adoption. 7. Transparency and Traceability FAIR Value: Clear data lineage enables auditability and transparency of data transformations. Business Impact: Improves stakeholder confidence (e.g. investors, regulators) and facilitates sustainable ESG reporting. 8. Strategic Data Asset Stewardship FAIR Value: Recognises data as a long-term, lifecycle-managed asset. Business Impact: Supports enterprise valuation, improves M&A readiness, and facilitates long-term business resilience.
